{
    "search_metadata": {
        "id": "637004f1aa6c958999ec948e",
        "status": "Success",
        "json_endpoint": "https://serpapi.com/searches/478f3495659252db/637004f1aa6c958999ec948e.json",
        "created_at": "2022-11-12 20:41:21 UTC",
        "processed_at": "2022-11-12 20:41:21 UTC",
        "google_maps_url": "https://www.google.com/search?q=restaurants&hl=en&tbm=map&tch=1&pb=!4m8!1m3!1d373045.2152138438!2d-89.3837613!3d43.074761!3m2!1i1024!2i768!4f13.1!7i20!8i60!10b1!12m25!1m1!18b1!2m3!5m1!6e2!20e3!6m16!4b1!23b1!26i1!27i1!41i2!45b1!49b1!63m0!67b1!73m0!74i150000!75b1!89b1!105b1!109b1!110m0!10b1!16b1!19m4!2m3!1i360!2i120!4i8!20m65!2m2!1i203!2i100!3m2!2i4!5b1!6m6!1m2!1i86!2i86!1m2!1i408!2i240!7m50!1m3!1e1!2b0!3e3!1m3!1e2!2b1!3e2!1m3!1e2!2b0!3e3!1m3!1e3!2b0!3e3!1m3!1e8!2b0!3e3!1m3!1e3!2b1!3e2!1m3!1e10!2b0!3e3!1m3!1e10!2b1!3e2!1m3!1e9!2b1!3e2!1m3!1e10!2b0!3e3!1m3!1e10!2b1!3e2!1m3!1e10!2b0!3e4!2b1!4b1!9b0!22m3!1s!2z!7e81!24m55!1m15!13m7!2b1!3b1!4b1!6i1!8b1!9b1!20b0!18m6!3b1!4b1!5b1!6b1!13b0!14b0!2b1!5m5!2b1!3b1!5b1!6b1!7b1!10m1!8e3!14m1!3b1!17b1!20m4!1e3!1e6!1e14!1e15!24b1!25b1!26b1!29b1!30m1!2b1!36b1!43b1!52b1!54m1!1b1!55b1!56m2!1b1!3b1!65m5!3m4!1m3!1m2!1i224!2i298!89b1!26m4!2m3!1i80!2i92!4i8!30m28!1m6!1m2!1i0!2i0!2m2!1i458!2i768!1m6!1m2!1i974!2i0!2m2!1i1024!2i768!1m6!1m2!1i0!2i0!2m2!1i1024!2i20!1m6!1m2!1i0!2i748!2m2!1i1024!2i768!34m16!2b1!3b1!4b1!6b1!8m4!1b1!3b1!4b1!6b1!9b1!12b1!14b1!20b1!23b1!25b1!26b1!37m1!1e81!42b1!46m1!1e9!47m0!49m1!3b1!50m53!1m49!2m7!1u3!4s!5e1!9s!10m2!3m1!1e1!2m7!1u2!4s!5e1!9s!10m2!2m1!1e1!2m7!1u16!4s!5e1!9s!10m2!16m1!1e1!2m7!1u16!4s!5e1!9s!10m2!16m1!1e2!3m11!1u16!2m4!1m2!16m1!1e1!2s!2m4!1m2!16m1!1e2!2s!3m1!1u2!3m1!1u3!4BIAE!2e2!3m1!3b1!59B!65m0!69i540",
        "raw_html_file": "https://serpapi.com/searches/478f3495659252db/637004f1aa6c958999ec948e.html",
        "prettify_html_file": "https://serpapi.com/searches/478f3495659252db/637004f1aa6c958999ec948e.prettify",
        "total_time_taken": 4.5
    },
    "search_parameters": {
        "engine": "google_maps",
        "type": "search",
        "q": "restaurants",
        "ll": "@43.074761,-89.3837613,10z",
        "google_domain": "google.com",
        "hl": "en",
        "start": 60
    },
    "search_information": {
        "local_results_state": "Results for exact spelling",
        "query_displayed": "restaurants"
    },
    "local_results": [
        {
            "position": 1,
            "title": "A&W Restaurant",
            "place_id": "ChIJAVi2iyNqB4gR3F0mhvYbKt8",
            "data_id": "0x88076a238bb65801:0xdf2a1bf686265ddc",
            "data_cid": "16080696165106343388",
            "reviews_link": "https://serpapi.com/search.json?data_id=0x88076a238bb65801%3A0xdf2a1bf686265ddc&engine=google_maps_reviews&hl=en",
            "photos_link": "https://serpapi.com/search.json?data_id=0x88076a238bb65801%3A0xdf2a1bf686265ddc&engine=google_maps_photos&hl=en",
            "gps_coordinates": {
                "latitude": 43.4596211,
                "longitude": -89.76948759999999
            },
            "place_id_search": "https://serpapi.com/search.json?data=%214m5%213m4%211s0x88076a238bb65801%3A0xdf2a1bf686265ddc%218m2%213d43.4596211%214d-89.76948759999999&engine=google_maps&google_domain=google.com&hl=en&start=60&type=place",
            "rating": 4,
            "reviews": 641,
            "price": "$",
            "type": "Fast food restaurant",
            "address": "900 US-12, Baraboo, WI 53913",
            "open_state": "Open \u22c5 Closes 10PM",
            "hours": "Open \u22c5 Closes 10PM",
            "operating_hours": {
                "saturday": "10AM\u201310PM",
                "sunday": "10AM\u201310PM",
                "monday": "10AM\u201310PM",
                "tuesday": "10AM\u201310PM",
                "wednesday": "10AM\u201310PM",
                "thursday": "10AM\u201310PM",
                "friday": "10AM\u201310PM"
            },
            "phone": "(608) 356-0747",
            "website": "https://www.awrestaurants.com/",
            "description": "Fast-food chain for burgers & root beer. Fast-food outlet serving up namesake root beer, plus burgers, chicken & fries.",
            "service_options": {
                "dine_in": true,
                "drive_through": true,
                "delivery": false
            },
            "thumbnail": "https://lh5.googleusercontent.com/p/AF1QipM-qe_f7fI68qsR8MvbkAn301Z3aT-mEpvyb7Cx=w80-h106-k-no"
        },
        {
            "position": 2,
            "title": "Coachman\u2019s Restaurant",
            "place_id": "ChIJcaOBxQpqBogRs62vI1f0YLw",
            "data_id": "0x88066a0ac581a371:0xbc60f45723afadb3",
            "data_cid": "13574117931992722867",
            "reviews_link": "https://serpapi.com/search.json?data_id=0x88066a0ac581a371%3A0xbc60f45723afadb3&engine=google_maps_reviews&hl=en",
            "photos_link": "https://serpapi.com/search.json?data_id=0x88066a0ac581a371%3A0xbc60f45723afadb3&engine=google_maps_photos&hl=en",
            "gps_coordinates": {
                "latitude": 42.9192707,
                "longitude": -89.0927052
            },
            "place_id_search": "https://serpapi.com/search.json?data=%214m5%213m4%211s0x88066a0ac581a371%3A0xbc60f45723afadb3%218m2%213d42.9192707%214d-89.0927052&engine=google_maps&google_domain=google.com&hl=en&start=60&type=place",
            "rating": 4.3,
            "reviews": 37,
            "unclaimed_listing": true,
            "type": "Restaurant",
            "address": "984 County Hwy A, Edgerton, WI 53534",
            "open_state": "Open \u22c5 Closes 9PM",
            "hours": "Open \u22c5 Closes 9PM",
            "operating_hours": {
                "saturday": "11AM\u20139PM",
                "sunday": "9AM\u20139PM",
                "monday": "11AM\u20139PM",
                "tuesday": "11AM\u20139PM",
                "wednesday": "11AM\u20139PM",
                "thursday": "11AM\u20139PM",
                "friday": "11AM\u20139PM"
            },
            "phone": "(608) 884-8484",
            "website": "https://coachmans.com/dining-at-coachmans/",
            "service_options": {
                "dine_in": true,
                "takeout": true,
                "delivery": false
            }
        },
        {
            "position": 3,
            "title": "Erin's Snug Irish Pub and Restaurant",
            "place_id": "ChIJISaZ_ktWBogR5lAHVRsgdr4",
            "data_id": "0x8806564bfe992621:0xbe76201b550750e6",
            "data_cid": "13724192216220913894",
            "reviews_link": "https://serpapi.com/search.json?data_id=0x8806564bfe992621%3A0xbe76201b550750e6&engine=google_maps_reviews&hl=en",
            "photos_link": "https://serpapi.com/search.json?data_id=0x8806564bfe992621%3A0xbe76201b550750e6&engine=google_maps_photos&hl=en",
            "gps_coordinates": {
                "latitude": 43.1485267,
                "longitude": -89.2892703
            },
            "place_id_search": "https://serpapi.com/search.json?data=%214m5%213m4%211s0x8806564bfe992621%3A0xbe76201b550750e6%218m2%213d43.1485267%214d-89.2892703&engine=google_maps&google_domain=google.com&hl=en&start=60&type=place",
            "rating": 4.3,
            "reviews": 1754,
            "price": "$$",
            "type": "Irish pub",
            "address": "4601 American Pkwy, Madison, WI 53718",
            "open_state": "Open \u22c5 Closes 10PM",
            "hours": "Open \u22c5 Closes 10PM",
            "operating_hours": {
                "saturday": "11AM\u201310PM",
                "sunday": "11AM\u20139PM",
                "monday": "11AM\u20139:30PM",
                "tuesday": "11AM\u20139:30PM",
                "wednesday": "11AM\u20139:30PM",
                "thursday": "11AM\u20139:30PM",
                "friday": "11AM\u201310PM"
            },
            "phone": "(608) 242-7616",
            "website": "http://www.erinssnug.com/",
            "description": "Irish tavern with a traditional look. Irish tavern fare, many beers on tap & 16 TVs in an old-world setting of dark wood & fireplaces.",
            "service_options": {
                "dine_in": true,
                "curbside_pickup": true,
                "delivery": false
            },
            "thumbnail": "https://lh5.googleusercontent.com/p/AF1QipNm3bBRripmG9c0dcKgr0hgRv2q_xG3v3cqOrkP=w80-h106-k-no"
        },
        {
            "position": 4,
            "title": "Madistan Indian Restaurant",
            "place_id": "ChIJoe9QmzZTBogRAzg7N4EwUp4",
            "data_id": "0x880653369b50efa1:0x9e523081373b3803",
            "data_cid": "11408234137618429955",
            "reviews_link": "https://serpapi.com/search.json?data_id=0x880653369b50efa1%3A0x9e523081373b3803&engine=google_maps_reviews&hl=en",
            "photos_link": "https://serpapi.com/search.json?data_id=0x880653369b50efa1%3A0x9e523081373b3803&engine=google_maps_photos&hl=en",
            "gps_coordinates": {
                "latitude": 43.073053,
                "longitude": -89.393772
            },
            "place_id_search": "https://serpapi.com/search.json?data=%214m5%213m4%211s0x880653369b50efa1%3A0x9e523081373b3803%218m2%213d43.073053%214d-89.393772&engine=google_maps&google_domain=google.com&hl=en&start=60&type=place",
            "rating": 4.1,
            "reviews": 346,
            "price": "$",
            "type": "Indian restaurant",
            "address": "317 N Bassett St, Madison, WI 53703",
            "open_state": "Open \u22c5 Closes 3AM",
            "hours": "Open \u22c5 Closes 3AM",
            "operating_hours": {
                "saturday": "1PM\u20133AM",
                "sunday": "Closed",
                "monday": "11AM\u20139PM",
                "tuesday": "11AM\u20139PM",
                "wednesday": "11AM\u20139PM",
                "thursday": "11AM\u20139PM",
                "friday": "1PM\u20133AM"
            },
            "phone": "(608) 422-5422",
            "website": "http://madistanwi.com/",
            "description": "Basic Pakistani & Mediterranean eatery. Unfussy counter-service place offering Pakistani, Indian & Mediterranean food favorites.",
            "service_options": {
                "dine_in": true,
                "takeout": true,
                "no_contact_delivery": true
            },
            "thumbnail": "https://lh5.googleusercontent.com/p/AF1QipN2SsJjhGYiRxd_vLgseg2zoCt36W61ckNTcG8v=w122-h92-k-no"
        },
        {
            "position": 5,
            "title": "4 Sisters Family Restaurant",
            "place_id": "ChIJS3pWG793BogRT5itT5RMRyE",
            "data_id": "0x880677bf1b567a4b:0x21474c944fad984f",
            "data_cid": "2397969526473726031",
            "reviews_link": "https://serpapi.com/search.json?data_id=0x880677bf1b567a4b%3A0x21474c944fad984f&engine=google_maps_reviews&hl=en",
            "photos_link": "https://serpapi.com/search.json?data_id=0x880677bf1b567a4b%3A0x21474c944fad984f&engine=google_maps_photos&hl=en",
            "gps_coordinates": {
                "latitude": 42.9911794,
                "longitude": -88.8087025
            },
            "place_id_search": "https://serpapi.com/search.json?data=%214m5%213m4%211s0x880677bf1b567a4b%3A0x21474c944fad984f%218m2%213d42.9911794%214d-88.8087025&engine=google_maps&google_domain=google.com&hl=en&start=60&type=place",
            "rating": 4.2,
            "reviews": 334,
            "price": "$",
            "type": "Family restaurant",
            "address": "149 Collins Rd #2019, Jefferson, WI 53549",
            "open_state": "Closed \u22c5 Opens 7AM Sun",
            "hours": "Closed \u22c5 Opens 7AM Sun",
            "operating_hours": {
                "saturday": "7AM\u20132PM",
                "sunday": "7AM\u20132PM",
                "monday": "7AM\u20132PM",
                "tuesday": "7AM\u20132PM",
                "wednesday": "7AM\u20132PM",
                "thursday": "7AM\u20132PM",
                "friday": "7AM\u20138PM"
            },
            "phone": "(920) 541-3700",
            "website": "http://4-sisters-family-restaurant.business.site/",
            "service_options": {
                "dine_in": true,
                "takeout": true,
                "delivery": false
            },
            "thumbnail": "https://lh5.googleusercontent.com/p/AF1QipMXCstKNbnH7pPf7cdCYCRcmEwGzVLOAENmiLsZ=w80-h106-k-no"
        },
        {
            "position": 6,
            "title": "The Cheesecake Factory",
            "place_id": "ChIJz1vLf_iuB4gR5ksFpZxE_5w",
            "data_id": "0x8807aef87fcb5bcf:0x9cff449ca5054be6",
            "data_cid": "11312836228552149990",
            "reviews_link": "https://serpapi.com/search.json?data_id=0x8807aef87fcb5bcf%3A0x9cff449ca5054be6&engine=google_maps_reviews&hl=en",
            "photos_link": "https://serpapi.com/search.json?data_id=0x8807aef87fcb5bcf%3A0x9cff449ca5054be6&engine=google_maps_photos&hl=en",
            "gps_coordinates": {
                "latitude": 43.057573,
                "longitude": -89.5048796
            },
            "place_id_search": "https://serpapi.com/search.json?data=%214m5%213m4%211s0x8807aef87fcb5bcf%3A0x9cff449ca5054be6%218m2%213d43.057573%214d-89.5048796&engine=google_maps&google_domain=google.com&hl=en&start=60&type=place",
            "rating": 4.1,
            "reviews": 2055,
            "price": "$$",
            "type": "Restaurant",
            "address": "1 W Towne Mall, Madison, WI 53719",
            "open_state": "Open \u22c5 Closes 11PM",
            "hours": "Open \u22c5 Closes 11PM",
            "operating_hours": {
                "saturday": "11AM\u201311PM",
                "sunday": "10AM\u201310PM",
                "monday": "11AM\u201310PM",
                "tuesday": "11AM\u201310PM",
                "wednesday": "11AM\u201310PM",
                "thursday": "11AM\u201310PM",
                "friday": "11AM\u201311PM"
            },
            "phone": "(608) 824-2370",
            "website": "https://locations.thecheesecakefactory.com/wi/madison-190.html?utm_source=Google&utm_medium=Maps&utm_campaign=Google+Places",
            "description": "American dining chain with jumbo plates. American chain restaurant offering sizable portions from a vast menu including signature cheesecake",
            "service_options": {
                "dine_in": true,
                "curbside_pickup": true,
                "delivery": true
            },
            "thumbnail": "https://lh5.googleusercontent.com/p/AF1QipNhgoq263s3mSX3XXiQOq46nr2hwRX6E9sdNlL9=w164-h92-k-no"
        },
        {
            "position": 7,
            "title": "Los Atlantes Mexican Restaurant & Bakery",
            "place_id": "ChIJW5oDQgmuB4gRnh4IiWUsQaQ",
            "data_id": "0x8807ae0942039a5b:0xa4412c6589081e9e",
            "data_cid": "11835790110308703902",
            "reviews_link": "https://serpapi.com/search.json?data_id=0x8807ae0942039a5b%3A0xa4412c6589081e9e&engine=google_maps_reviews&hl=en",
            "photos_link": "https://serpapi.com/search.json?data_id=0x8807ae0942039a5b%3A0xa4412c6589081e9e&engine=google_maps_photos&hl=en",
            "gps_coordinates": {
                "latitude": 43.0324838,
                "longitude": -89.47776979999999
            },
            "place_id_search": "https://serpapi.com/search.json?data=%214m5%213m4%211s0x8807ae0942039a5b%3A0xa4412c6589081e9e%218m2%213d43.0324838%214d-89.47776979999999&engine=google_maps&google_domain=google.com&hl=en&start=60&type=place",
            "rating": 4.2,
            "reviews": 353,
            "price": "$",
            "type": "Mexican restaurant",
            "address": "5706 Raymond Rd, Madison, WI 53711",
            "open_state": "Open \u22c5 Closes 8PM",
            "hours": "Open \u22c5 Closes 8PM",
            "operating_hours": {
                "saturday": "8AM\u20138PM",
                "sunday": "8AM\u20137PM",
                "monday": "8AM\u20138PM",
                "tuesday": "8AM\u20138PM",
                "wednesday": "8AM\u20138PM",
                "thursday": "8AM\u20138PM",
                "friday": "8AM\u20138PM"
            },
            "phone": "(608) 285-9135",
            "website": "http://losatlanteswisconsin.com/",
            "description": "Modest option for traditional meals. Casual restaurant offering Mexican meals & baked goods in a modest, contemporary space.",
            "service_options": {
                "dine_in": true,
                "takeout": true,
                "no_contact_delivery": true
            },
            "thumbnail": "https://lh5.googleusercontent.com/p/AF1QipOUGCQDz5dOW9sIMUotK4AjooZx4hCB3NzvLyZU=w163-h92-k-no"
        },
        {
            "position": 8,
            "title": "Nani Restaurant",
            "place_id": "ChIJowNSL1-uB4gRp05_569OSfE",
            "data_id": "0x8807ae5f2f5203a3:0xf1494eafe77f4ea7",
            "data_cid": "17386514353850633895",
            "reviews_link": "https://serpapi.com/search.json?data_id=0x8807ae5f2f5203a3%3A0xf1494eafe77f4ea7&engine=google_maps_reviews&hl=en",
            "photos_link": "https://serpapi.com/search.json?data_id=0x8807ae5f2f5203a3%3A0xf1494eafe77f4ea7&engine=google_maps_photos&hl=en",
            "gps_coordinates": {
                "latitude": 43.0551329,
                "longitude": -89.4974568
            },
            "place_id_search": "https://serpapi.com/search.json?data=%214m5%213m4%211s0x8807ae5f2f5203a3%3A0xf1494eafe77f4ea7%218m2%213d43.0551329%214d-89.4974568&engine=google_maps&google_domain=google.com&hl=en&start=60&type=place",
            "rating": 4.3,
            "reviews": 742,
            "price": "$$",
            "type": "Chinese restaurant",
            "address": "518 Grand Canyon Dr, Madison, WI 53719",
            "open_state": "Closes soon \u22c5 3PM \u22c5 Reopens 4:30PM",
            "hours": "Closes soon \u22c5 3PM \u22c5 Reopens 4:30PM",
            "operating_hours": {
                "saturday": "11AM\u20133PM",
                "sunday": "11AM\u20133PM",
                "monday": "11AM\u20133PM",
                "tuesday": "11AM\u20133PM",
                "wednesday": "Closed",
                "thursday": "11AM\u20133PM",
                "friday": "11AM\u20133PM"
            },
            "phone": "(608) 826-9300",
            "website": "http://nanimadison.com/",
            "description": "Roomy Chinese place featuring dim sum. Spacious, tranquil Chinese restaurant offering dim sum & other Cantonese & Sichuan specialties.",
            "service_options": {
                "dine_in": true,
                "curbside_pickup": true,
                "no_contact_delivery": true
            },
            "thumbnail": "https://lh5.googleusercontent.com/p/AF1QipNGG8bjBGM0MSotj07ghCcrNJj2KNfElfpixTHe=w135-h92-k-no"
        },
        {
            "position": 9,
            "title": "A&W Restaurant",
            "place_id": "ChIJpzsTRhgVBogR9TtmvEaGu7U",
            "data_id": "0x8806151846133ba7:0xb5bb8646bc663bf5",
            "data_cid": "13095207979876498421",
            "reviews_link": "https://serpapi.com/search.json?data_id=0x8806151846133ba7%3A0xb5bb8646bc663bf5&engine=google_maps_reviews&hl=en",
            "photos_link": "https://serpapi.com/search.json?data_id=0x8806151846133ba7%3A0xb5bb8646bc663bf5&engine=google_maps_photos&hl=en",
            "gps_coordinates": {
                "latitude": 42.8387873,
                "longitude": -89.0643413
            },
            "place_id_search": "https://serpapi.com/search.json?data=%214m5%213m4%211s0x8806151846133ba7%3A0xb5bb8646bc663bf5%218m2%213d42.8387873%214d-89.0643413&engine=google_maps&google_domain=google.com&hl=en&start=60&type=place",
            "rating": 4.4,
            "reviews": 574,
            "price": "$",
            "type": "Fast food restaurant",
            "address": "601 N Main St, Edgerton, WI 53534",
            "open_state": "Open \u22c5 Closes 7PM",
            "hours": "Open \u22c5 Closes 7PM",
            "operating_hours": {
                "saturday": "11AM\u20137PM",
                "sunday": "11AM\u20137PM",
                "monday": "11AM\u20137PM",
                "tuesday": "11AM\u20137PM",
                "wednesday": "11AM\u20137PM",
                "thursday": "11AM\u20137PM",
                "friday": "11AM\u20137PM"
            },
            "phone": "(608) 884-8412",
            "website": "https://www.awrestaurants.com/",
            "description": "Fast-food chain for burgers & root beer. Fast-food outlet serving up namesake root beer, plus burgers, chicken & fries.",
            "service_options": {
                "dine_in": true,
                "drive_through": true,
                "delivery": false
            },
            "thumbnail": "https://lh5.googleusercontent.com/p/AF1QipMJUjpzenC3rRECU_-vwT51rzR4FgT3Ga5J-t6O=w122-h92-k-no"
        },
        {
            "position": 10,
            "title": "Nattspil",
            "place_id": "ChIJRQmp2T9TBogRUmenzgdjqbc",
            "data_id": "0x8806533fd9a90945:0xb7a96307cea76752",
            "data_cid": "13234217865187911506",
            "reviews_link": "https://serpapi.com/search.json?data_id=0x8806533fd9a90945%3A0xb7a96307cea76752&engine=google_maps_reviews&hl=en",
            "photos_link": "https://serpapi.com/search.json?data_id=0x8806533fd9a90945%3A0xb7a96307cea76752&engine=google_maps_photos&hl=en",
            "gps_coordinates": {
                "latitude": 43.074431399999995,
                "longitude": -89.3797501
            },
            "place_id_search": "https://serpapi.com/search.json?data=%214m5%213m4%211s0x8806533fd9a90945%3A0xb7a96307cea76752%218m2%213d43.074431399999995%214d-89.3797501&engine=google_maps&google_domain=google.com&hl=en&start=60&type=place",
            "rating": 4.7,
            "reviews": 669,
            "price": "$$",
            "type": "Eclectic restaurant",
            "address": "211 King St, Madison, WI 53703",
            "open_state": "Closed \u22c5 Opens 5PM",
            "hours": "Closed \u22c5 Opens 5PM",
            "operating_hours": {
                "saturday": "5PM\u20131AM",
                "sunday": "5PM\u20131AM",
                "monday": "5PM\u20131AM",
                "tuesday": "5PM\u20131AM",
                "wednesday": "5PM\u20131AM",
                "thursday": "5PM\u20131AM",
                "friday": "5PM\u20131AM"
            },
            "website": "http://www.nattspil.com/",
            "description": "Hip hideaway for drinks & small plates. Hidden, cash-only haunt offering global small plates, cocktails & beer in an intimate space.",
            "service_options": {
                "dine_in": true,
                "takeout": true,
                "delivery": false
            },
            "thumbnail": "https://lh5.googleusercontent.com/p/AF1QipMGtItsltmFpDoddx5xadU2NcIMMYrxgbkh3g1T=w122-h92-k-no"
        },
        {
            "position": 11,
            "title": "North Of The Bayou Restaurant & Brewery",
            "place_id": "ChIJhQThVhVTBogR8nT_6pYN0CQ",
            "data_id": "0x8806531556e10485:0x24d00d96eaff74f2",
            "data_cid": "2652635122360087794",
            "reviews_link": "https://serpapi.com/search.json?data_id=0x8806531556e10485%3A0x24d00d96eaff74f2&engine=google_maps_reviews&hl=en",
            "photos_link": "https://serpapi.com/search.json?data_id=0x8806531556e10485%3A0x24d00d96eaff74f2&engine=google_maps_photos&hl=en",
            "gps_coordinates": {
                "latitude": 43.085234799999995,
                "longitude": -89.3095463
            },
            "place_id_search": "https://serpapi.com/search.json?data=%214m5%213m4%211s0x8806531556e10485%3A0x24d00d96eaff74f2%218m2%213d43.085234799999995%214d-89.3095463&engine=google_maps&google_domain=google.com&hl=en&start=60&type=place",
            "rating": 4.2,
            "reviews": 419,
            "price": "$$",
            "type": "Brewery",
            "address": "802 Atlas Ave, Madison, WI 53714",
            "open_state": "Opens soon \u22c5 3PM",
            "hours": "Opens soon \u22c5 3PM",
            "operating_hours": {
                "saturday": "3\u20138PM",
                "sunday": "Closed",
                "monday": "Closed",
                "tuesday": "Closed",
                "wednesday": "3\u20138PM",
                "thursday": "3\u20138PM",
                "friday": "3\u20138PM"
            },
            "phone": "(608) 286-1393",
            "website": "https://m.facebook.com/TheBayouMadison/",
            "description": "French Quarter-inspired Cajun spot. Casual restaurant serving Cajun fare & Mardi Gras-themed drinks in French Quarter-style digs.",
            "service_options": {
                "dine_in": true,
                "curbside_pickup": true,
                "no_contact_delivery": true
            },
            "thumbnail": "https://lh5.googleusercontent.com/p/AF1QipNiTm4JCuVlQFWQoZkrUsxWV_rcJoJQChZMC-I1=w163-h92-k-no"
        },
        {
            "position": 12,
            "title": "Don Maguey Mexican Restaurant",
            "place_id": "ChIJOXEVo2ZZBogRr_LYZrBp30M",
            "data_id": "0x88065966a3157139:0x43df69b066d8f2af",
            "data_cid": "4890743926708302511",
            "reviews_link": "https://serpapi.com/search.json?data_id=0x88065966a3157139%3A0x43df69b066d8f2af&engine=google_maps_reviews&hl=en",
            "photos_link": "https://serpapi.com/search.json?data_id=0x88065966a3157139%3A0x43df69b066d8f2af&engine=google_maps_photos&hl=en",
            "gps_coordinates": {
                "latitude": 43.107315,
                "longitude": -89.1985778
            },
            "place_id_search": "https://serpapi.com/search.json?data=%214m5%213m4%211s0x88065966a3157139%3A0x43df69b066d8f2af%218m2%213d43.107315%214d-89.1985778&engine=google_maps&google_domain=google.com&hl=en&start=60&type=place",
            "rating": 4.5,
            "reviews": 223,
            "type": "Mexican restaurant",
            "address": "1609 Landmark Dr Suite 101, Cottage Grove, WI 53527",
            "open_state": "Open \u22c5 Closes 10:30PM",
            "hours": "Open \u22c5 Closes 10:30PM",
            "operating_hours": {
                "saturday": "11AM\u201310:30PM",
                "sunday": "11AM\u20139PM",
                "monday": "11AM\u201310PM",
                "tuesday": "11AM\u201310PM",
                "wednesday": "11AM\u201310PM",
                "thursday": "11AM\u201310PM",
                "friday": "11AM\u201310:30PM"
            },
            "phone": "(608) 688-2056",
            "website": "https://donmagueymexicanrestaurant.com/",
            "service_options": {
                "dine_in": true,
                "curbside_pickup": true,
                "delivery": false
            },
            "thumbnail": "https://lh5.googleusercontent.com/p/AF1QipOibi48atzN7Mzpc4ZJ5JznezFA7B-0YuUEqaAg=w80-h106-k-no"
        },
        {
            "position": 13,
            "title": "Aurota",
            "place_id": "ChIJpXOsNDxTBogRKGWsEfpv_V8",
            "data_id": "0x8806533c34ac73a5:0x5ffd6ffa11ac6528",
            "data_cid": "6916807722539967784",
            "reviews_link": "https://serpapi.com/search.json?data_id=0x8806533c34ac73a5%3A0x5ffd6ffa11ac6528&engine=google_maps_reviews&hl=en",
            "photos_link": "https://serpapi.com/search.json?data_id=0x8806533c34ac73a5%3A0x5ffd6ffa11ac6528&engine=google_maps_photos&hl=en",
            "gps_coordinates": {
                "latitude": 43.074912999999995,
                "longitude": -89.386999
            },
            "place_id_search": "https://serpapi.com/search.json?data=%214m5%213m4%211s0x8806533c34ac73a5%3A0x5ffd6ffa11ac6528%218m2%213d43.074912999999995%214d-89.386999&engine=google_maps&google_domain=google.com&hl=en&start=60&type=place",
            "unclaimed_listing": true,
            "type": "Restaurant",
            "address": "100 State St, Madison, WI 53703",
            "service_options": {
                "dine_in": true,
                "takeout": true,
                "delivery": false
            },
            "thumbnail": "https://streetviewpixels-pa.googleapis.com/v1/thumbnail?panoid=sPf-RgTW9VN6T7VTnPGR9Q&cb_client=search.gws-prod.gps&w=80&h=92&yaw=214.20685&pitch=0&thumbfov=100"
        },
        {
            "position": 14,
            "title": "Fish Tales Restaurant",
            "place_id": "ChIJSRaW1SMSB4gRcIFLoTdQaI4",
            "data_id": "0x88071223d5961649:0x8e685037a14b8170",
            "data_cid": "10261539950823178608",
            "reviews_link": "https://serpapi.com/search.json?data_id=0x88071223d5961649%3A0x8e685037a14b8170&engine=google_maps_reviews&hl=en",
            "photos_link": "https://serpapi.com/search.json?data_id=0x88071223d5961649%3A0x8e685037a14b8170&engine=google_maps_photos&hl=en",
            "gps_coordinates": {
                "latitude": 43.350874,
                "longitude": -89.62994599999999
            },
            "place_id_search": "https://serpapi.com/search.json?data=%214m5%213m4%211s0x88071223d5961649%3A0x8e685037a14b8170%218m2%213d43.350874%214d-89.62994599999999&engine=google_maps&google_domain=google.com&hl=en&start=60&type=place",
            "rating": 4.4,
            "reviews": 348,
            "price": "$$",
            "type": "American restaurant",
            "address": "W12690 WI-188, Lodi, WI 53555",
            "open_state": "Closed \u22c5 Opens 4PM Wed",
            "hours": "Closed \u22c5 Opens 4PM Wed",
            "operating_hours": {
                "saturday": "Closed",
                "sunday": "Closed",
                "monday": "Closed",
                "tuesday": "Closed",
                "wednesday": "4\u20139PM",
                "thursday": "4\u20139PM",
                "friday": "4\u20139PM"
            },
            "phone": "(608) 592-4266",
            "website": "http://www.fishtalesrestaurant.com/",
            "description": "Traditional surf 'n' turf supper club. Classic seafood & steak specialties, plus pizza, in a bar & restaurant with rustic atmosphere.",
            "service_options": {
                "dine_in": true,
                "takeout": true,
                "delivery": false
            },
            "thumbnail": "https://lh5.googleusercontent.com/p/AF1QipOaZ_Raa3HGK1wJID3Cv99LPfAR-DS5YHP4HquQ=w80-h106-k-no"
        },
        {
            "position": 15,
            "title": "Villa Dolce",
            "place_id": "ChIJq-wWVNWuB4gRcjO4yHiHpaw",
            "data_id": "0x8807aed55416ecab:0xaca58778c8b83372",
            "data_cid": "12440498498514203506",
            "reviews_link": "https://serpapi.com/search.json?data_id=0x8807aed55416ecab%3A0xaca58778c8b83372&engine=google_maps_reviews&hl=en",
            "photos_link": "https://serpapi.com/search.json?data_id=0x8807aed55416ecab%3A0xaca58778c8b83372&engine=google_maps_photos&hl=en",
            "gps_coordinates": {
                "latitude": 43.095594,
                "longitude": -89.5117223
            },
            "place_id_search": "https://serpapi.com/search.json?data=%214m5%213m4%211s0x8807aed55416ecab%3A0xaca58778c8b83372%218m2%213d43.095594%214d-89.5117223&engine=google_maps&google_domain=google.com&hl=en&start=60&type=place",
            "rating": 4.6,
            "reviews": 418,
            "price": "$$",
            "type": "Italian restaurant",
            "address": "1828 Parmenter St, Middleton, WI 53562",
            "open_state": "Closed \u22c5 Opens 5PM",
            "hours": "Closed \u22c5 Opens 5PM",
            "operating_hours": {
                "saturday": "5\u20139PM",
                "sunday": "Closed",
                "monday": "5\u20139PM",
                "tuesday": "5\u20139PM",
                "wednesday": "5\u20139PM",
                "thursday": "5\u20139PM",
                "friday": "5\u20139PM"
            },
            "phone": "(608) 833-0033",
            "website": "https://www.villadolcecafe.com/",
            "description": "Basic spot for artisanal pizza & gelato. Relaxed eatery offering artisanal pizza, housemade gelato & wine in a contemporary setting.",
            "service_options": {
                "dine_in": true,
                "curbside_pickup": true,
                "no_contact_delivery": true
            },
            "thumbnail": "https://lh5.googleusercontent.com/p/AF1QipPp0WNXHxK3HFZ8z1LW-z5mJjMDK8LyVLipZDU=w122-h92-k-no"
        },
        {
            "position": 16,
            "title": "Salvatore's Tomato Pies",
            "place_id": "ChIJCc_kIcX3BogRhL61990uTvs",
            "data_id": "0x8806f7c521e4cf09:0xfb4e2eddf7b5be84",
            "data_cid": "18108462682581876356",
            "reviews_link": "https://serpapi.com/search.json?data_id=0x8806f7c521e4cf09%3A0xfb4e2eddf7b5be84&engine=google_maps_reviews&hl=en",
            "photos_link": "https://serpapi.com/search.json?data_id=0x8806f7c521e4cf09%3A0xfb4e2eddf7b5be84&engine=google_maps_photos&hl=en",
            "gps_coordinates": {
                "latitude": 43.1830188,
                "longitude": -89.2128489
            },
            "place_id_search": "https://serpapi.com/search.json?data=%214m5%213m4%211s0x8806f7c521e4cf09%3A0xfb4e2eddf7b5be84%218m2%213d43.1830188%214d-89.2128489&engine=google_maps&google_domain=google.com&hl=en&start=60&type=place",
            "rating": 4.6,
            "reviews": 1176,
            "price": "$$",
            "type": "Pizza restaurant",
            "address": "121 E Main St, Sun Prairie, WI 53590",
            "open_state": "Open \u22c5 Closes 9PM",
            "hours": "Open \u22c5 Closes 9PM",
            "operating_hours": {
                "saturday": "11AM\u20139PM",
                "sunday": "11AM\u20139PM",
                "monday": "Closed",
                "tuesday": "4\u20139PM",
                "wednesday": "4\u20139PM",
                "thursday": "4\u20139PM",
                "friday": "11AM\u20139PM"
            },
            "phone": "(608) 318-1761",
            "website": "https://www.salvatorestomatopies.com/sun-prairie-menus/",
            "description": "Classic spot for artisanal pies & brews. Traditional, family-friendly pizzeria with locally sourced, unique toppings on handcrafted crust.",
            "service_options": {
                "dine_in": true,
                "curbside_pickup": true,
                "no_contact_delivery": true
            },
            "editorial_reviews": {
                "summary": "Where to Eat and Drink in Madison Right Now",
                "link": "https://www.thrillist.com/eat/milwaukee/best-restaurants-in-madison-wisconsin",
                "thumbnail": "//www.google.com/s2/favicons?domain=www.thrillist.com&sz=16"
            },
            "thumbnail": "https://lh5.googleusercontent.com/p/AF1QipPi7meDomy-zyENPjM_QcVDBx_SvMGyZ8lzq1Ja=w122-h92-k-no"
        },
        {
            "position": 17,
            "title": "Hacienda Real Mexican Restaurant",
            "place_id": "ChIJEQQ_B5QQBogR-ZH7fU1geG8",
            "data_id": "0x88061094073f0411:0x6f78604d7dfb91f9",
            "data_cid": "8032275821357666809",
            "reviews_link": "https://serpapi.com/search.json?data_id=0x88061094073f0411%3A0x6f78604d7dfb91f9&engine=google_maps_reviews&hl=en",
            "photos_link": "https://serpapi.com/search.json?data_id=0x88061094073f0411%3A0x6f78604d7dfb91f9&engine=google_maps_photos&hl=en",
            "gps_coordinates": {
                "latitude": 42.7182198,
                "longitude": -88.9943313
            },
            "place_id_search": "https://serpapi.com/search.json?data=%214m5%213m4%211s0x88061094073f0411%3A0x6f78604d7dfb91f9%218m2%213d42.7182198%214d-88.9943313&engine=google_maps&google_domain=google.com&hl=en&start=60&type=place",
            "rating": 4.5,
            "reviews": 1906,
            "price": "$$",
            "type": "Mexican restaurant",
            "address": "3001 N Lexington Dr, Janesville, WI 53545",
            "open_state": "Open \u22c5 Closes 10PM",
            "hours": "Open \u22c5 Closes 10PM",
            "operating_hours": {
                "saturday": "11AM\u201310PM",
                "sunday": "11AM\u20139PM",
                "monday": "11AM\u20139PM",
                "tuesday": "11AM\u20139PM",
                "wednesday": "11AM\u20139PM",
                "thursday": "11AM\u20139PM",
                "friday": "11AM\u201310PM"
            },
            "phone": "(608) 754-8835",
            "website": "http://haciendarealwi.com/",
            "description": "Lively spot for south-of-the-border eats. Festive eatery serving Tex Mex plates & flavored margaritas amid colorful hand-painted decor.",
            "service_options": {
                "dine_in": true,
                "curbside_pickup": true,
                "no_contact_delivery": true
            },
            "thumbnail": "https://lh5.googleusercontent.com/p/AF1QipOU6QhGwI-UTzHi2t1b_vzuWtqnr8bAtbmfdfP2=w122-h92-k-no"
        },
        {
            "position": 18,
            "title": "Avantis Italian Restaurant & Pub",
            "place_id": "ChIJ26_Yi2iwB4gRAkzTNXgsZG8",
            "data_id": "0x8807b0688bd8afdb:0x6f642c7835d34c02",
            "data_cid": "8026589330691804162",
            "reviews_link": "https://serpapi.com/search.json?data_id=0x8807b0688bd8afdb%3A0x6f642c7835d34c02&engine=google_maps_reviews&hl=en",
            "photos_link": "https://serpapi.com/search.json?data_id=0x8807b0688bd8afdb%3A0x6f642c7835d34c02&engine=google_maps_photos&hl=en",
            "gps_coordinates": {
                "latitude": 42.9897108,
                "longitude": -89.53318379999999
            },
            "place_id_search": "https://serpapi.com/search.json?data=%214m5%213m4%211s0x8807b0688bd8afdb%3A0x6f642c7835d34c02%218m2%213d42.9897108%214d-89.53318379999999&engine=google_maps&google_domain=google.com&hl=en&start=60&type=place",
            "rating": 4.2,
            "reviews": 369,
            "price": "$$",
            "type": "Italian restaurant",
            "address": "119 S Main St #1, Verona, WI 53593",
            "open_state": "Closed \u22c5 Opens 4PM",
            "hours": "Closed \u22c5 Opens 4PM",
            "operating_hours": {
                "saturday": "4\u20139PM",
                "sunday": "Closed",
                "monday": "4\u20139PM",
                "tuesday": "4\u20139PM",
                "wednesday": "4\u20139PM",
                "thursday": "4\u20139PM",
                "friday": "4\u20139PM"
            },
            "phone": "(608) 848-3315",
            "website": "http://www.avantisverona.com/",
            "description": "Relaxed hub for Italian eats & cocktails. Classic pastas, pizzas & other Italian eats star at this homey, relaxed venue with a full bar.",
            "service_options": {
                "dine_in": true,
                "takeout": true,
                "no_contact_delivery": true
            },
            "thumbnail": "https://lh5.googleusercontent.com/p/AF1QipMVAFBYCCkKhgpwPeMl3q9NaewXEoWZjvlY2Vnq=w189-h92-k-no"
        },
        {
            "position": 19,
            "title": "Dubai Mediterranean Restaurant and Bar",
            "place_id": "ChIJf9veQTZTBogRMjqyZMgoWEM",
            "data_id": "0x8806533641dedb7f:0x435828c864b23a32",
            "data_cid": "4852673439639681586",
            "reviews_link": "https://serpapi.com/search.json?data_id=0x8806533641dedb7f%3A0x435828c864b23a32&engine=google_maps_reviews&hl=en",
            "photos_link": "https://serpapi.com/search.json?data_id=0x8806533641dedb7f%3A0x435828c864b23a32&engine=google_maps_photos&hl=en",
            "gps_coordinates": {
                "latitude": 43.0747066,
                "longitude": -89.3926465
            },
            "place_id_search": "https://serpapi.com/search.json?data=%214m5%213m4%211s0x8806533641dedb7f%3A0x435828c864b23a32%218m2%213d43.0747066%214d-89.3926465&engine=google_maps&google_domain=google.com&hl=en&start=60&type=place",
            "rating": 4.1,
            "reviews": 361,
            "price": "$$",
            "type": "Mediterranean restaurant",
            "address": "419 State St, Madison, WI 53703",
            "open_state": "Open \u22c5 Closes 1:30AM",
            "hours": "Open \u22c5 Closes 1:30AM",
            "operating_hours": {
                "saturday": "11AM\u20131:30AM",
                "sunday": "11AM\u201312AM",
                "monday": "11AM\u20131:30AM",
                "tuesday": "11AM\u20131:30AM",
                "wednesday": "11AM\u20131:30AM",
                "thursday": "11AM\u20131:30AM",
                "friday": "11AM\u20131:30AM"
            },
            "phone": "(608) 819-8222",
            "website": "http://www.dubaimadison.com/",
            "description": "Classic fare in contemporary surrounds. Relaxed, modern place serving traditional Mediterranean plates with house wines & unique beers.",
            "service_options": {
                "dine_in": true,
                "curbside_pickup": true,
                "no_contact_delivery": true
            },
            "thumbnail": "https://lh5.googleusercontent.com/p/AF1QipNbuNpdpzP-8YdN9Rw4_pAdc6zRuDXgv1qaDmlr=w122-h92-k-no"
        },
        {
            "position": 20,
            "title": "Himal Chuli Restaurant",
            "place_id": "ChIJnyd8uDdTBogR9MZ5lTH1SYI",
            "data_id": "0x88065337b87c279f:0x8249f5319579c6f4",
            "data_cid": "9388304491540498164",
            "reviews_link": "https://serpapi.com/search.json?data_id=0x88065337b87c279f%3A0x8249f5319579c6f4&engine=google_maps_reviews&hl=en",
            "photos_link": "https://serpapi.com/search.json?data_id=0x88065337b87c279f%3A0x8249f5319579c6f4&engine=google_maps_photos&hl=en",
            "gps_coordinates": {
                "latitude": 43.074938499999995,
                "longitude": -89.39070509999999
            },
            "place_id_search": "https://serpapi.com/search.json?data=%214m5%213m4%211s0x88065337b87c279f%3A0x8249f5319579c6f4%218m2%213d43.074938499999995%214d-89.39070509999999&engine=google_maps&google_domain=google.com&hl=en&start=60&type=place",
            "rating": 4.5,
            "reviews": 588,
            "price": "$$",
            "unclaimed_listing": true,
            "type": "Nepalese restaurant",
            "address": "318 State St, Madison, WI 53703",
            "open_state": "Open \u22c5 Closes 8:30PM",
            "hours": "Open \u22c5 Closes 8:30PM",
            "operating_hours": {
                "saturday": "12\u20138:30PM",
                "sunday": "12\u20138:30PM",
                "monday": "Closed",
                "tuesday": "11AM\u20138:30PM",
                "wednesday": "11AM\u20138:30PM",
                "thursday": "11AM\u20138:30PM",
                "friday": "11AM\u20138:30PM"
            },
            "phone": "(608) 251-9225",
            "website": "https://himalchulirestaurant.com/",
            "description": "Snug spot for traditional Nepalese fare. Pint-sized spot with an outdoor patio featuring Nepalese cuisine, including many vegetarian dishes.",
            "service_options": {
                "dine_in": true,
                "takeout": true,
                "no_contact_delivery": true
            },
            "thumbnail": "https://lh5.googleusercontent.com/p/AF1QipM8BnJfl3RETd5qM4lzzOaYWsvP1Ms3cGTe_UvG=w80-h142-k-no"
        }
    ],
    "serpapi_pagination": {
        "next": "https://serpapi.com/search.json?engine=google_maps&google_domain=google.com&hl=en&ll=%4043.074761%2C-89.3837613%2C10z&q=restaurants&start=80&type=search",
        "current": "https://serpapi.com/search.json?engine=google_maps&google_domain=google.com&hl=en&ll=%4043.074761%2C-89.3837613%2C10z&q=restaurants&start=60&type=search",
        "previous": "https://serpapi.com/search.json?engine=google_maps&google_domain=google.com&hl=en&ll=%4043.074761%2C-89.3837613%2C10z&q=restaurants&start=40&type=search"
    }
}