{
    "search_metadata": {
        "id": "6370048d9c84ac3b40e30657",
        "status": "Success",
        "json_endpoint": "https://serpapi.com/searches/4d1e630b2f97b9d0/6370048d9c84ac3b40e30657.json",
        "created_at": "2022-11-12 20:39:41 UTC",
        "processed_at": "2022-11-12 20:39:41 UTC",
        "google_maps_url": "https://www.google.com/search?q=restaurants&hl=en&tbm=map&tch=1&pb=!4m8!1m3!1d10876.984160295779!2d-89.3837613!3d43.074761!3m2!1i1024!2i768!4f13.1!7i20!8i180!10b1!12m25!1m1!18b1!2m3!5m1!6e2!20e3!6m16!4b1!23b1!26i1!27i1!41i2!45b1!49b1!63m0!67b1!73m0!74i150000!75b1!89b1!105b1!109b1!110m0!10b1!16b1!19m4!2m3!1i360!2i120!4i8!20m65!2m2!1i203!2i100!3m2!2i4!5b1!6m6!1m2!1i86!2i86!1m2!1i408!2i240!7m50!1m3!1e1!2b0!3e3!1m3!1e2!2b1!3e2!1m3!1e2!2b0!3e3!1m3!1e3!2b0!3e3!1m3!1e8!2b0!3e3!1m3!1e3!2b1!3e2!1m3!1e10!2b0!3e3!1m3!1e10!2b1!3e2!1m3!1e9!2b1!3e2!1m3!1e10!2b0!3e3!1m3!1e10!2b1!3e2!1m3!1e10!2b0!3e4!2b1!4b1!9b0!22m3!1s!2z!7e81!24m55!1m15!13m7!2b1!3b1!4b1!6i1!8b1!9b1!20b0!18m6!3b1!4b1!5b1!6b1!13b0!14b0!2b1!5m5!2b1!3b1!5b1!6b1!7b1!10m1!8e3!14m1!3b1!17b1!20m4!1e3!1e6!1e14!1e15!24b1!25b1!26b1!29b1!30m1!2b1!36b1!43b1!52b1!54m1!1b1!55b1!56m2!1b1!3b1!65m5!3m4!1m3!1m2!1i224!2i298!89b1!26m4!2m3!1i80!2i92!4i8!30m28!1m6!1m2!1i0!2i0!2m2!1i458!2i768!1m6!1m2!1i974!2i0!2m2!1i1024!2i768!1m6!1m2!1i0!2i0!2m2!1i1024!2i20!1m6!1m2!1i0!2i748!2m2!1i1024!2i768!34m16!2b1!3b1!4b1!6b1!8m4!1b1!3b1!4b1!6b1!9b1!12b1!14b1!20b1!23b1!25b1!26b1!37m1!1e81!42b1!46m1!1e9!47m0!49m1!3b1!50m53!1m49!2m7!1u3!4s!5e1!9s!10m2!3m1!1e1!2m7!1u2!4s!5e1!9s!10m2!2m1!1e1!2m7!1u16!4s!5e1!9s!10m2!16m1!1e1!2m7!1u16!4s!5e1!9s!10m2!16m1!1e2!3m11!1u16!2m4!1m2!16m1!1e1!2s!2m4!1m2!16m1!1e2!2s!3m1!1u2!3m1!1u3!4BIAE!2e2!3m1!3b1!59B!65m0!69i540",
        "raw_html_file": "https://serpapi.com/searches/4d1e630b2f97b9d0/6370048d9c84ac3b40e30657.html",
        "prettify_html_file": "https://serpapi.com/searches/4d1e630b2f97b9d0/6370048d9c84ac3b40e30657.prettify",
        "total_time_taken": 3.17
    },
    "search_parameters": {
        "engine": "google_maps",
        "type": "search",
        "q": "restaurants",
        "ll": "@43.074761,-89.3837613,15.1z",
        "google_domain": "google.com",
        "hl": "en",
        "start": 180
    },
    "search_information": {
        "local_results_state": "Results for exact spelling",
        "query_displayed": "restaurants"
    },
    "local_results": [
        {
            "position": 1,
            "title": "McDonald's",
            "place_id": "ChIJh1NSwo5S-YcR7eiDSdw1UeE",
            "data_id": "0x87f9528ec2525387:0xe15135dc4983e8ed",
            "data_cid": "16235817351889807597",
            "reviews_link": "https://serpapi.com/search.json?data_id=0x87f9528ec2525387%3A0xe15135dc4983e8ed&engine=google_maps_reviews&hl=en",
            "photos_link": "https://serpapi.com/search.json?data_id=0x87f9528ec2525387%3A0xe15135dc4983e8ed&engine=google_maps_photos&hl=en",
            "gps_coordinates": {
                "latitude": 43.9238782,
                "longitude": -91.2449647
            },
            "place_id_search": "https://serpapi.com/search.json?data=%214m5%213m4%211s0x87f9528ec2525387%3A0xe15135dc4983e8ed%218m2%213d43.9238782%214d-91.2449647&engine=google_maps&google_domain=google.com&hl=en&start=180&type=place",
            "rating": 3.6,
            "reviews": 626,
            "price": "$",
            "type": "Fast food restaurant",
            "address": "3924 Circle Dr, Holmen, WI 54636",
            "open_state": "Open \u22c5 Closes 12AM",
            "hours": "Open \u22c5 Closes 12AM",
            "operating_hours": {
                "saturday": "6AM\u201312AM",
                "sunday": "6AM\u201311PM",
                "monday": "6AM\u201311PM",
                "tuesday": "6AM\u201311PM",
                "wednesday": "6AM\u201311PM",
                "thursday": "6AM\u201311PM",
                "friday": "6AM\u201312AM"
            },
            "phone": "(608) 781-2588",
            "website": "https://www.mcdonalds.com/us/en-us/location/WI/HOLMEN/3924-CIRCLE-DR/17228.html?cid=RF:YXT:GMB::Clicks",
            "description": "Iconic fast-food burger & fries chain. Classic, long-running fast-food chain known for its burgers & fries.",
            "service_options": {
                "dine_in": true,
                "drive_through": true,
                "delivery": true
            },
            "thumbnail": "https://lh5.googleusercontent.com/p/AF1QipNg4XNyAot3LT3QVWaWkHfL8bxBJE0kJbEz-UFs=w122-h92-k-no"
        },
        {
            "position": 2,
            "title": "Muy Caliente Taco Broz llc",
            "place_id": "ChIJXd7QKddV-YcRrK0mo-h9nfM",
            "data_id": "0x87f955d729d0de5d:0xf39d7de8a326adac",
            "data_cid": "17554325360683167148",
            "reviews_link": "https://serpapi.com/search.json?data_id=0x87f955d729d0de5d%3A0xf39d7de8a326adac&engine=google_maps_reviews&hl=en",
            "photos_link": "https://serpapi.com/search.json?data_id=0x87f955d729d0de5d%3A0xf39d7de8a326adac&engine=google_maps_photos&hl=en",
            "gps_coordinates": {
                "latitude": 43.810727799999995,
                "longitude": -91.25255059999999
            },
            "place_id_search": "https://serpapi.com/search.json?data=%214m5%213m4%211s0x87f955d729d0de5d%3A0xf39d7de8a326adac%218m2%213d43.810727799999995%214d-91.25255059999999&engine=google_maps&google_domain=google.com&hl=en&start=180&type=place",
            "rating": 4.8,
            "reviews": 6,
            "type": "Mexican restaurant",
            "address": "Downtown, La Crosse, WI 54601",
            "phone": "(608) 863-6033",
            "service_options": {
                "dine_in": true,
                "takeout": true
            },
            "thumbnail": "https://lh5.googleusercontent.com/p/AF1QipPQM-JW8A6EpA42wazNI0H-HmukctJKI-v8vR5b=w80-h177-k-no"
        },
        {
            "position": 3,
            "title": "Subway",
            "place_id": "ChIJsY8j7Y5S-YcRfqCXCWtDc48",
            "data_id": "0x87f9528eed238fb1:0x8f73436b0997a07e",
            "data_cid": "10336679696746913918",
            "reviews_link": "https://serpapi.com/search.json?data_id=0x87f9528eed238fb1%3A0x8f73436b0997a07e&engine=google_maps_reviews&hl=en",
            "photos_link": "https://serpapi.com/search.json?data_id=0x87f9528eed238fb1%3A0x8f73436b0997a07e&engine=google_maps_photos&hl=en",
            "gps_coordinates": {
                "latitude": 43.9238534,
                "longitude": -91.24424239999999
            },
            "place_id_search": "https://serpapi.com/search.json?data=%214m5%213m4%211s0x87f9528eed238fb1%3A0x8f73436b0997a07e%218m2%213d43.9238534%214d-91.24424239999999&engine=google_maps&google_domain=google.com&hl=en&start=180&type=place",
            "rating": 4.1,
            "reviews": 127,
            "price": "$",
            "type": "Sandwich shop",
            "address": "3920 Circle Dr, Holmen, WI 54636",
            "open_state": "Open \u22c5 Closes 9PM",
            "hours": "Open \u22c5 Closes 9PM",
            "operating_hours": {
                "saturday": "8AM\u20139PM",
                "sunday": "8AM\u20139PM",
                "monday": "8AM\u20139PM",
                "tuesday": "8AM\u20139PM",
                "wednesday": "8AM\u20139PM",
                "thursday": "8AM\u20139PM",
                "friday": "8AM\u20139PM"
            },
            "phone": "(608) 783-1444",
            "website": "https://restaurants.subway.com/united-states/wi/holmen/3920-circle-drive?utm_source=yxt-goog&utm_medium=local&utm_term=acq&utm_content=27218&utm_campaign=evergreen-2020&y_source=1_MTQ5MDAyNTAtNzE1LWxvY2F0aW9uLndlYnNpdGU%3D",
            "description": "Build-your-own sandwich chain. Casual counter-serve chain for build-your-own sandwiches & salads, with health-conscious options.",
            "service_options": {
                "dine_in": true,
                "drive_through": true,
                "delivery": true
            },
            "thumbnail": "https://lh5.googleusercontent.com/p/AF1QipNCB0CKIEVwKanNdI7TaKjBnQo4CnZAQFq0lcb3=w81-h92-k-no"
        },
        {
            "position": 4,
            "title": "Subway",
            "place_id": "ChIJ1TWhHqWs_ocRb3buHKN7_F0",
            "data_id": "0x87feaca51ea135d5:0x5dfc7ba31cee766f",
            "data_cid": "6772423880153658991",
            "reviews_link": "https://serpapi.com/search.json?data_id=0x87feaca51ea135d5%3A0x5dfc7ba31cee766f&engine=google_maps_reviews&hl=en",
            "photos_link": "https://serpapi.com/search.json?data_id=0x87feaca51ea135d5%3A0x5dfc7ba31cee766f&engine=google_maps_photos&hl=en",
            "gps_coordinates": {
                "latitude": 43.8691774,
                "longitude": -91.20058999999999
            },
            "place_id_search": "https://serpapi.com/search.json?data=%214m5%213m4%211s0x87feaca51ea135d5%3A0x5dfc7ba31cee766f%218m2%213d43.8691774%214d-91.20058999999999&engine=google_maps&google_domain=google.com&hl=en&start=180&type=place",
            "rating": 4,
            "reviews": 179,
            "price": "$",
            "type": "Sandwich shop",
            "address": "9360 WI-16, Onalaska, WI 54650",
            "open_state": "Open \u22c5 Closes 9PM",
            "hours": "Open \u22c5 Closes 9PM",
            "operating_hours": {
                "saturday": "8AM\u20139PM",
                "sunday": "8AM\u20139PM",
                "monday": "8AM\u20139PM",
                "tuesday": "8AM\u20139PM",
                "wednesday": "8AM\u20139PM",
                "thursday": "8AM\u20132PM",
                "friday": "8AM\u20139PM"
            },
            "phone": "(608) 781-7827",
            "website": "https://restaurants.subway.com/united-states/wi/onalaska/9360-state-rd?utm_source=yxt-goog&utm_medium=local&utm_term=acq&utm_content=5441&utm_campaign=evergreen-2020&y_source=1_MTQ5MDE5NzctNzE1LWxvY2F0aW9uLndlYnNpdGU%3D",
            "description": "Build-your-own sandwich chain. Casual counter-serve chain for build-your-own sandwiches & salads, with health-conscious options.",
            "service_options": {
                "dine_in": true,
                "takeout": true,
                "delivery": true
            },
            "thumbnail": "https://lh5.googleusercontent.com/p/AF1QipO0RcljjhFw-O12UqmVGROOGLHkq8gvJkU--w7N=w122-h92-k-no"
        },
        {
            "position": 5,
            "title": "Festival Sushi",
            "place_id": "ChIJYw1DsFOt_ocRsUjOHhlCUSs",
            "data_id": "0x87fead53b0430d63:0x2b5142191ece48b1",
            "data_cid": "3121348692402915505",
            "reviews_link": "https://serpapi.com/search.json?data_id=0x87fead53b0430d63%3A0x2b5142191ece48b1&engine=google_maps_reviews&hl=en",
            "photos_link": "https://serpapi.com/search.json?data_id=0x87fead53b0430d63%3A0x2b5142191ece48b1&engine=google_maps_photos&hl=en",
            "gps_coordinates": {
                "latitude": 43.8688886,
                "longitude": -91.2119069
            },
            "place_id_search": "https://serpapi.com/search.json?data=%214m5%213m4%211s0x87fead53b0430d63%3A0x2b5142191ece48b1%218m2%213d43.8688886%214d-91.2119069&engine=google_maps&google_domain=google.com&hl=en&start=180&type=place",
            "rating": 5,
            "reviews": 1,
            "unclaimed_listing": true,
            "type": "Asian restaurant",
            "address": "1260 Crossing Meadows Dr, Onalaska, WI 54650",
            "open_state": "Open \u22c5 Closes 9:30PM",
            "hours": "Open \u22c5 Closes 9:30PM",
            "operating_hours": {
                "saturday": "8AM\u20139:30PM",
                "sunday": "8AM\u20139:30PM",
                "monday": "8AM\u20139:30PM",
                "tuesday": "8AM\u20139:30PM",
                "wednesday": "8AM\u20139:30PM",
                "thursday": "8AM\u20139:30PM",
                "friday": "8AM\u20139:30PM"
            },
            "service_options": {
                "dine_in": true,
                "takeout": true,
                "delivery": false
            },
            "thumbnail": "https://lh5.googleusercontent.com/p/AF1QipPguY6trwSRfingnrfdjTaV9ibEBFoDQiM0ivGn=w80-h106-k-no"
        },
        {
            "position": 6,
            "title": "Subway",
            "place_id": "ChIJ-WWDU7FN-YcRiJlWLhP_zqs",
            "data_id": "0x87f94db1538365f9:0xabceff132e569988",
            "data_cid": "12380112883534961032",
            "reviews_link": "https://serpapi.com/search.json?data_id=0x87f94db1538365f9%3A0xabceff132e569988&engine=google_maps_reviews&hl=en",
            "photos_link": "https://serpapi.com/search.json?data_id=0x87f94db1538365f9%3A0xabceff132e569988&engine=google_maps_photos&hl=en",
            "gps_coordinates": {
                "latitude": 43.9698315,
                "longitude": -91.2649086
            },
            "place_id_search": "https://serpapi.com/search.json?data=%214m5%213m4%211s0x87f94db1538365f9%3A0xabceff132e569988%218m2%213d43.9698315%214d-91.2649086&engine=google_maps&google_domain=google.com&hl=en&start=180&type=place",
            "rating": 4,
            "reviews": 72,
            "price": "$",
            "type": "Sandwich shop",
            "address": "618 N Holmen Dr, Holmen, WI 54636",
            "open_state": "Open \u22c5 Closes 9PM",
            "hours": "Open \u22c5 Closes 9PM",
            "operating_hours": {
                "saturday": "8AM\u20139PM",
                "sunday": "8AM\u20139PM",
                "monday": "8AM\u20139PM",
                "tuesday": "8AM\u20139PM",
                "wednesday": "8AM\u20139PM",
                "thursday": "8AM\u20139PM",
                "friday": "8AM\u20139PM"
            },
            "phone": "(608) 526-2610",
            "website": "https://restaurants.subway.com/united-states/wi/holmen/618-n-holmen-dr?utm_source=yxt-goog&utm_medium=local&utm_term=acq&utm_content=16762&utm_campaign=evergreen-2020&y_source=1_MTQ5MDMyOTAtNzE1LWxvY2F0aW9uLndlYnNpdGU%3D",
            "description": "Build-your-own sandwich chain. Casual counter-serve chain for build-your-own sandwiches & salads, with health-conscious options.",
            "service_options": {
                "dine_in": true,
                "drive_through": true,
                "delivery": true
            },
            "thumbnail": "https://lh5.googleusercontent.com/p/AF1QipOv6bKDImprYAvw7AYpVOdS8j8ZwS-07KqyRMEd=w80-h106-k-no"
        },
        {
            "position": 7,
            "title": "Subway",
            "place_id": "ChIJI50kMaZV-YcRfNpJDbCrjyE",
            "data_id": "0x87f955a631249d23:0x218fabb00d49da7c",
            "data_cid": "2418340297546783356",
            "reviews_link": "https://serpapi.com/search.json?data_id=0x87f955a631249d23%3A0x218fabb00d49da7c&engine=google_maps_reviews&hl=en",
            "photos_link": "https://serpapi.com/search.json?data_id=0x87f955a631249d23%3A0x218fabb00d49da7c&engine=google_maps_photos&hl=en",
            "gps_coordinates": {
                "latitude": 43.8118238,
                "longitude": -91.2535218
            },
            "place_id_search": "https://serpapi.com/search.json?data=%214m5%213m4%211s0x87f955a631249d23%3A0x218fabb00d49da7c%218m2%213d43.8118238%214d-91.2535218&engine=google_maps&google_domain=google.com&hl=en&start=180&type=place",
            "rating": 4.2,
            "reviews": 124,
            "price": "$",
            "type": "Sandwich shop",
            "address": "202 3rd St S, La Crosse, WI 54601",
            "open_state": "Open \u22c5 Closes 9PM",
            "hours": "Open \u22c5 Closes 9PM",
            "operating_hours": {
                "saturday": "8AM\u20139PM",
                "sunday": "8AM\u20139PM",
                "monday": "8AM\u20139PM",
                "tuesday": "8AM\u20139PM",
                "wednesday": "8AM\u20139PM",
                "thursday": "8AM\u20139PM",
                "friday": "8AM\u20139PM"
            },
            "phone": "(608) 785-7827",
            "website": "https://restaurants.subway.com/united-states/wi/la-crosse/202-s-3rd-st?utm_source=yxt-goog&utm_medium=local&utm_term=acq&utm_content=27217&utm_campaign=evergreen-2020&y_source=1_MTQ4OTk1MjEtNzE1LWxvY2F0aW9uLndlYnNpdGU%3D",
            "description": "Build-your-own sandwich chain. Casual counter-serve chain for build-your-own sandwiches & salads, with health-conscious options.",
            "service_options": {
                "dine_in": true,
                "takeout": true,
                "delivery": true
            },
            "thumbnail": "https://lh5.googleusercontent.com/p/AF1QipMv0Pf6qVqnthphwNl9ELIeJ8dlN3RJ7yUtypoC=w80-h106-k-no"
        },
        {
            "position": 8,
            "title": "Shogun Sushi and Hibachi",
            "place_id": "ChIJk6_3TE1T-YcR3JN1ek-vBV0",
            "data_id": "0x87f9534d4cf7af93:0x5d05af4f7a7593dc",
            "data_cid": "6702956376302654428",
            "reviews_link": "https://serpapi.com/search.json?data_id=0x87f9534d4cf7af93%3A0x5d05af4f7a7593dc&engine=google_maps_reviews&hl=en",
            "photos_link": "https://serpapi.com/search.json?data_id=0x87f9534d4cf7af93%3A0x5d05af4f7a7593dc&engine=google_maps_photos&hl=en",
            "gps_coordinates": {
                "latitude": 43.871274299999996,
                "longitude": -91.2125506
            },
            "place_id_search": "https://serpapi.com/search.json?data=%214m5%213m4%211s0x87f9534d4cf7af93%3A0x5d05af4f7a7593dc%218m2%213d43.871274299999996%214d-91.2125506&engine=google_maps&google_domain=google.com&hl=en&start=180&type=place",
            "rating": 4.4,
            "reviews": 1206,
            "price": "$$",
            "type": "Japanese restaurant",
            "address": "Wisconsin, Onalaska, Crossing Meadows Dr, \u90ae\u653f\u7f16\u7801: 54650",
            "open_state": "Closes soon \u22c5 3PM \u22c5 Reopens 4:30PM",
            "hours": "Closes soon \u22c5 3PM \u22c5 Reopens 4:30PM",
            "operating_hours": {
                "saturday": "11AM\u20133PM",
                "sunday": "12\u20133PM",
                "monday": "11AM\u20133PM",
                "tuesday": "11AM\u20133PM",
                "wednesday": "11AM\u20133PM",
                "thursday": "11AM\u20133PM",
                "friday": "11AM\u20133PM"
            },
            "phone": "(608) 779-1188",
            "website": "http://www.shogunonalaska.com/",
            "service_options": {
                "dine_in": true,
                "takeout": true,
                "delivery": true
            },
            "thumbnail": "https://lh5.googleusercontent.com/p/AF1QipN7qlvZNy315Q5zsUWhvArqD1DkzlW5Yztv2JXP=w122-h92-k-no"
        },
        {
            "position": 9,
            "title": "Food Dudes",
            "place_id": "ChIJKX90qgxN-YcRitpSh0guKBc",
            "data_id": "0x87f94d0caa747f29:0x17282e488752da8a",
            "data_cid": "1668634550983645834",
            "reviews_link": "https://serpapi.com/search.json?data_id=0x87f94d0caa747f29%3A0x17282e488752da8a&engine=google_maps_reviews&hl=en",
            "photos_link": "https://serpapi.com/search.json?data_id=0x87f94d0caa747f29%3A0x17282e488752da8a&engine=google_maps_photos&hl=en",
            "gps_coordinates": {
                "latitude": 43.960265799999995,
                "longitude": -91.2628843
            },
            "place_id_search": "https://serpapi.com/search.json?data=%214m5%213m4%211s0x87f94d0caa747f29%3A0x17282e488752da8a%218m2%213d43.960265799999995%214d-91.2628843&engine=google_maps&google_domain=google.com&hl=en&start=180&type=place",
            "rating": 5,
            "reviews": 6,
            "type": "Fast food restaurant",
            "address": "208 S Holmen Dr Suite 100, Holmen, WI 54636",
            "open_state": "Open \u22c5 Closes 8PM",
            "hours": "Open \u22c5 Closes 8PM",
            "operating_hours": {
                "saturday": "11AM\u20138PM",
                "sunday": "11AM\u20136PM",
                "monday": "Closed",
                "tuesday": "11AM\u20138PM",
                "wednesday": "11AM\u20138PM",
                "thursday": "11AM\u20138PM",
                "friday": "11AM\u20138PM"
            },
            "service_options": {
                "dine_in": true,
                "takeout": true,
                "delivery": false
            },
            "thumbnail": "https://lh5.googleusercontent.com/p/AF1QipOoc43kTika0Rk-eoSqbOH9j6sx6Bj0Qg9fs8Nf=w80-h106-k-no"
        },
        {
            "position": 10,
            "title": "Eataly",
            "place_id": "ChIJe_Fq2lctDogRTpK221p4Fmg",
            "data_id": "0x880e2d57da6af17b:0x6816785adbb6924e",
            "data_cid": "7500314561060704846",
            "reviews_link": "https://serpapi.com/search.json?data_id=0x880e2d57da6af17b%3A0x6816785adbb6924e&engine=google_maps_reviews&hl=en",
            "photos_link": "https://serpapi.com/search.json?data_id=0x880e2d57da6af17b%3A0x6816785adbb6924e&engine=google_maps_photos&hl=en",
            "gps_coordinates": {
                "latitude": 41.892099099999996,
                "longitude": -87.6259524
            },
            "place_id_search": "https://serpapi.com/search.json?data=%214m5%213m4%211s0x880e2d57da6af17b%3A0x6816785adbb6924e%218m2%213d41.892099099999996%214d-87.6259524&engine=google_maps&google_domain=google.com&hl=en&start=180&type=place",
            "rating": 4.3,
            "reviews": 971,
            "price": "$$$",
            "type": "Italian restaurant",
            "address": "43 E Ohio St, Chicago, IL 60611",
            "open_state": "Open \u22c5 Closes 11PM",
            "hours": "Open \u22c5 Closes 11PM",
            "operating_hours": {
                "saturday": "8AM\u201311PM",
                "sunday": "8AM\u201310PM",
                "monday": "8AM\u201310PM",
                "tuesday": "8AM\u201310PM",
                "wednesday": "8AM\u201310PM",
                "thursday": "8AM\u201310PM",
                "friday": "8AM\u201311PM"
            },
            "phone": "(312) 521-8700",
            "website": "https://www.eataly.com/us_en/stores/chicago/",
            "description": "Buzzy locale for Italian classics. Bustling modern trattoria in an Italian marketplace for Neapolitan pizza & homemade, al dente pasta.",
            "service_options": {
                "dine_in": true,
                "takeout": true,
                "no_contact_delivery": true
            },
            "editorial_reviews": {
                "summary": "Chicago\u2019s Best Pizza",
                "link": "http://www.chicagomag.com/Chicago-Magazine/November-2019/Chicagos-Best-Pizza/",
                "thumbnail": "//www.google.com/s2/favicons?domain=www.chicagomag.com&sz=16"
            },
            "thumbnail": "https://lh5.googleusercontent.com/p/AF1QipMZTUE3nm7Z-adXfrS9v01C5ajwTIdE0UNdqmoT=w122-h92-k-no"
        },
        {
            "position": 11,
            "title": "Alinea",
            "place_id": "ChIJuyI60yLTD4gROwTWENq1He0",
            "data_id": "0x880fd322d33a22bb:0xed1db5da10d6043b",
            "data_cid": "17086012509503489083",
            "reviews_link": "https://serpapi.com/search.json?data_id=0x880fd322d33a22bb%3A0xed1db5da10d6043b&engine=google_maps_reviews&hl=en",
            "photos_link": "https://serpapi.com/search.json?data_id=0x880fd322d33a22bb%3A0xed1db5da10d6043b&engine=google_maps_photos&hl=en",
            "gps_coordinates": {
                "latitude": 41.913435,
                "longitude": -87.6480552
            },
            "place_id_search": "https://serpapi.com/search.json?data=%214m5%213m4%211s0x880fd322d33a22bb%3A0xed1db5da10d6043b%218m2%213d41.913435%214d-87.6480552&engine=google_maps&google_domain=google.com&hl=en&start=180&type=place",
            "rating": 4.6,
            "reviews": 2017,
            "price": "$$$$",
            "type": "Fine dining restaurant",
            "address": "1723 N Halsted St, Chicago, IL 60614",
            "open_state": "Closed \u22c5 Opens 5PM",
            "hours": "Closed \u22c5 Opens 5PM",
            "operating_hours": {
                "saturday": "5\u201310PM",
                "sunday": "5\u201310PM",
                "monday": "5\u201310PM",
                "tuesday": "5\u201310PM",
                "wednesday": "5\u201310PM",
                "thursday": "5\u201310PM",
                "friday": "5\u201310PM"
            },
            "website": "http://www.alinearestaurant.com/",
            "description": "New American foodie destination. Chef Grant Achatz draws foodies with New American tasting menus featuring highly creative plates.",
            "service_options": {
                "dine_in": true,
                "takeout": true,
                "delivery": false
            },
            "editorial_reviews": {
                "summary": "The 60 best restaurants for delivery and takeout in Chicago",
                "link": "https://www.timeout.com/chicago/restaurants/best-chicago-restaurant-delivery",
                "thumbnail": "//www.google.com/s2/favicons?domain=www.timeout.com&sz=16"
            },
            "thumbnail": "https://lh5.googleusercontent.com/p/AF1QipOFR2V_gaKJghwA_qyIRm0sRkls2tgpL6BVEai2=w157-h92-k-no"
        },
        {
            "position": 12,
            "title": "Jersey Mike's Subs",
            "place_id": "ChIJY6Tsajat_ocRNN28BKetK18",
            "data_id": "0x87fead366aeca463:0x5f2bada704bcdd34",
            "data_cid": "6857765790452342068",
            "reviews_link": "https://serpapi.com/search.json?data_id=0x87fead366aeca463%3A0x5f2bada704bcdd34&engine=google_maps_reviews&hl=en",
            "photos_link": "https://serpapi.com/search.json?data_id=0x87fead366aeca463%3A0x5f2bada704bcdd34&engine=google_maps_photos&hl=en",
            "gps_coordinates": {
                "latitude": 43.8674131,
                "longitude": -91.20601839999999
            },
            "place_id_search": "https://serpapi.com/search.json?data=%214m5%213m4%211s0x87fead366aeca463%3A0x5f2bada704bcdd34%218m2%213d43.8674131%214d-91.20601839999999&engine=google_maps&google_domain=google.com&hl=en&start=180&type=place",
            "rating": 4.5,
            "reviews": 367,
            "price": "$",
            "type": "Sandwich shop",
            "address": "1200 County Rd PH, Onalaska, WI 54650",
            "open_state": "Open \u22c5 Closes 9PM",
            "hours": "Open \u22c5 Closes 9PM",
            "operating_hours": {
                "saturday": "10AM\u20139PM",
                "sunday": "10AM\u20139PM",
                "monday": "10AM\u20139PM",
                "tuesday": "10AM\u20139PM",
                "wednesday": "10AM\u20139PM",
                "thursday": "10AM\u20139PM",
                "friday": "10AM\u20139PM"
            },
            "phone": "(608) 781-4175",
            "website": "https://www.jerseymikes.com/29017",
            "description": "Casual, counter-serve sandwich chain. New Jersey\u2013based counter-serve sandwich chain serving jumbo subs filled with cold cuts & toppings.",
            "service_options": {
                "dine_in": true,
                "drive_through": true,
                "no_contact_delivery": true
            },
            "thumbnail": "https://lh5.googleusercontent.com/p/AF1QipNiktNenJWAdcAPrjmScIR5zx_Oz86fjQH6QkET=w122-h92-k-no"
        },
        {
            "position": 13,
            "title": "Hy-Vee Market Grille",
            "place_id": "ChIJdX_GjFOr_ocROJpR1Vg6FAI",
            "data_id": "0x87feab538cc67f75:0x2143a58d5519a38",
            "data_cid": "149808840820496952",
            "reviews_link": "https://serpapi.com/search.json?data_id=0x87feab538cc67f75%3A0x2143a58d5519a38&engine=google_maps_reviews&hl=en",
            "photos_link": "https://serpapi.com/search.json?data_id=0x87feab538cc67f75%3A0x2143a58d5519a38&engine=google_maps_photos&hl=en",
            "gps_coordinates": {
                "latitude": 43.869646599999996,
                "longitude": -91.1957394
            },
            "place_id_search": "https://serpapi.com/search.json?data=%214m5%213m4%211s0x87feab538cc67f75%3A0x2143a58d5519a38%218m2%213d43.869646599999996%214d-91.1957394&engine=google_maps&google_domain=google.com&hl=en&start=180&type=place",
            "rating": 4,
            "reviews": 1,
            "price": "$$",
            "type": "Bar & grill",
            "address": "4200 WI-16, La Crosse, WI 54601",
            "open_state": "Open \u22c5 Closes 11PM",
            "hours": "Open \u22c5 Closes 11PM",
            "operating_hours": {
                "saturday": "5AM\u201311PM",
                "sunday": "5AM\u201311PM",
                "monday": "5AM\u201311PM",
                "tuesday": "5AM\u201311PM",
                "wednesday": "5AM\u201311PM",
                "thursday": "5AM\u201311PM",
                "friday": "5AM\u201311PM"
            },
            "phone": "(608) 668-6600",
            "website": "https://www.hy-vee.com/stores/detail.aspx?s=4280&utm_source=google&utm_medium=organic&utm_campaign=gmb-listing",
            "description": "Eatery with American food, beer & brunch. Casual spot with a varied American menu, a full bar with a large craft beer list & Sunday brunch.",
            "service_options": {
                "dine_in": true,
                "takeout": true
            },
            "thumbnail": "https://lh5.googleusercontent.com/p/AF1QipNs_hR0Cg4Vv7rtKSIJB8LIwB5AalzQycQ0cGY_=w204-h92-k-no"
        },
        {
            "position": 14,
            "title": "The King Of Tacos",
            "place_id": "ChIJccY4Ov1V-YcRP_Rhk7708T8",
            "data_id": "0x87f955fd3a38c671:0x3ff1f4be9361f43f",
            "data_cid": "4607732993130361919",
            "reviews_link": "https://serpapi.com/search.json?data_id=0x87f955fd3a38c671%3A0x3ff1f4be9361f43f&engine=google_maps_reviews&hl=en",
            "photos_link": "https://serpapi.com/search.json?data_id=0x87f955fd3a38c671%3A0x3ff1f4be9361f43f&engine=google_maps_photos&hl=en",
            "gps_coordinates": {
                "latitude": 43.832354099999996,
                "longitude": -91.23919509999999
            },
            "place_id_search": "https://serpapi.com/search.json?data=%214m5%213m4%211s0x87f955fd3a38c671%3A0x3ff1f4be9361f43f%218m2%213d43.832354099999996%214d-91.23919509999999&engine=google_maps&google_domain=google.com&hl=en&start=180&type=place",
            "type": "Mexican restaurant",
            "address": "418 Lang Dr, La Crosse, WI 54603",
            "open_state": "Open \u22c5 Closes 7:30AM Sun",
            "hours": "Open \u22c5 Closes 7:30AM Sun",
            "operating_hours": {
                "saturday": "12PM\u20137:30AM",
                "sunday": "12PM\u20137:30AM",
                "monday": "Closed",
                "tuesday": "Closed",
                "wednesday": "Closed",
                "thursday": "12PM\u20137:30AM",
                "friday": "12PM\u20137:30AM"
            },
            "phone": "(608) 633-9423",
            "service_options": {
                "takeout": true,
                "dine_in": false,
                "delivery": false
            },
            "thumbnail": "https://lh5.googleusercontent.com/p/AF1QipNEOB4nVw_HwgkP6LPNQ3TSAvF3qyEDhRq72IZ_=w122-h92-k-no"
        },
        {
            "position": 15,
            "title": "Levy",
            "place_id": "ChIJuZtDXFHTD4gRXbUgtM91NIc",
            "data_id": "0x880fd3515c439bb9:0x873475cfb420b55d",
            "data_cid": "9742541428849947997",
            "reviews_link": "https://serpapi.com/search.json?data_id=0x880fd3515c439bb9%3A0x873475cfb420b55d&engine=google_maps_reviews&hl=en",
            "photos_link": "https://serpapi.com/search.json?data_id=0x880fd3515c439bb9%3A0x873475cfb420b55d&engine=google_maps_photos&hl=en",
            "gps_coordinates": {
                "latitude": 41.9005388,
                "longitude": -87.6245928
            },
            "place_id_search": "https://serpapi.com/search.json?data=%214m5%213m4%211s0x880fd3515c439bb9%3A0x873475cfb420b55d%218m2%213d41.9005388%214d-87.6245928&engine=google_maps&google_domain=google.com&hl=en&start=180&type=place",
            "rating": 3.7,
            "reviews": 12,
            "unclaimed_listing": true,
            "type": "Caterer",
            "address": "980 N Michigan Ave, Chicago, IL 60611",
            "open_state": "Closed \u22c5 Opens 9AM Mon",
            "hours": "Closed \u22c5 Opens 9AM Mon",
            "operating_hours": {
                "saturday": "Closed",
                "sunday": "Closed",
                "monday": "9AM\u20133PM",
                "tuesday": "9AM\u20133PM",
                "wednesday": "9AM\u20133PM",
                "thursday": "9AM\u20133PM",
                "friday": "9AM\u20133PM"
            },
            "phone": "(312) 664-8200",
            "website": "http://www.levyrestaurants.com/",
            "thumbnail": "//lh5.googleusercontent.com/proxy/Ye7OYPUhncwUQuATbV0phfDzNoekgfBhhbFElwWu9nmAHtxbIgrqJrMuXApAx_x9Lz42Gemkp5kZaMEEfko7EXpKC7YxeLYpo_vetaQgLAgFxTXrVyfLbEl0rk-5OV_nf270PKUzyPmOLT4FtxYAn-mys-c1FYT7tp_5QCv_5hoL=w163-h92-k-no"
        },
        {
            "position": 16,
            "title": "Der Dutchman",
            "place_id": "ChIJ9yQ-Z46_OIgR9gdYex_uZ3o",
            "data_id": "0x8838bf8e673e24f7:0x7a67ee1f7b5807f6",
            "data_cid": "8820280214209169398",
            "reviews_link": "https://serpapi.com/search.json?data_id=0x8838bf8e673e24f7%3A0x7a67ee1f7b5807f6&engine=google_maps_reviews&hl=en",
            "photos_link": "https://serpapi.com/search.json?data_id=0x8838bf8e673e24f7%3A0x7a67ee1f7b5807f6&engine=google_maps_photos&hl=en",
            "gps_coordinates": {
                "latitude": 40.1051445,
                "longitude": -83.2779693
            },
            "place_id_search": "https://serpapi.com/search.json?data=%214m5%213m4%211s0x8838bf8e673e24f7%3A0x7a67ee1f7b5807f6%218m2%213d40.1051445%214d-83.2779693&engine=google_maps&google_domain=google.com&hl=en&start=180&type=place",
            "rating": 4.5,
            "reviews": 7487,
            "price": "$$",
            "type": "Family restaurant",
            "address": "445 S Jefferson Ave, Plain City, OH 43064",
            "open_state": "Open \u22c5 Closes 8PM",
            "hours": "Open \u22c5 Closes 8PM",
            "operating_hours": {
                "saturday": "7AM\u20138PM",
                "sunday": "Closed",
                "monday": "7AM\u20138PM",
                "tuesday": "7AM\u20138PM",
                "wednesday": "7AM\u20138PM",
                "thursday": "7AM\u20138PM",
                "friday": "7AM\u20138PM"
            },
            "phone": "(614) 873-3414",
            "website": "http://www.dhgroup.com/",
            "description": "Roomy venue for Amish fare. A large, straightforward dining room serving hearty Amish-style dishes such as roast beef & pot pie.",
            "service_options": {
                "dine_in": true,
                "curbside_pickup": true,
                "delivery": true
            },
            "thumbnail": "https://lh5.googleusercontent.com/p/AF1QipM5CIa1Z2DR3_-43nwRyyz4qvxDkcm5g2TuUedT=w163-h92-k-no"
        },
        {
            "position": 17,
            "title": "Der Dutchman",
            "place_id": "ChIJN0tY_7bAOYgRPS6BhmvcY2Y",
            "data_id": "0x8839c0b6ff584b37:0x6663dc6b86812e3d",
            "data_cid": "7377982968939228733",
            "reviews_link": "https://serpapi.com/search.json?data_id=0x8839c0b6ff584b37%3A0x6663dc6b86812e3d&engine=google_maps_reviews&hl=en",
            "photos_link": "https://serpapi.com/search.json?data_id=0x8839c0b6ff584b37%3A0x6663dc6b86812e3d&engine=google_maps_photos&hl=en",
            "gps_coordinates": {
                "latitude": 40.6448858,
                "longitude": -82.5427782
            },
            "place_id_search": "https://serpapi.com/search.json?data=%214m5%213m4%211s0x8839c0b6ff584b37%3A0x6663dc6b86812e3d%218m2%213d40.6448858%214d-82.5427782&engine=google_maps&google_domain=google.com&hl=en&start=180&type=place",
            "rating": 4.3,
            "reviews": 3836,
            "price": "$$",
            "type": "Restaurant",
            "address": "720 State Rte 97 W, Bellville, OH 44813",
            "open_state": "Open \u22c5 Closes 8PM",
            "hours": "Open \u22c5 Closes 8PM",
            "operating_hours": {
                "saturday": "7AM\u20138PM",
                "sunday": "Closed",
                "monday": "7AM\u20138PM",
                "tuesday": "7AM\u20138PM",
                "wednesday": "7AM\u20138PM",
                "thursday": "7AM\u20138PM",
                "friday": "7AM\u20138PM"
            },
            "phone": "(419) 886-7070",
            "website": "https://dhgroup.com/restaurants/der-dutchman-bellville-oh",
            "description": "Family-friendly American buffet. Down-home American joint offering hot & cold buffets of traditional comfort fare, plus a salad bar.",
            "service_options": {
                "dine_in": true,
                "curbside_pickup": true,
                "delivery": true
            },
            "thumbnail": "https://lh5.googleusercontent.com/p/AF1QipMYNLMSHGZheAI09knwKFZprNv2kYGhEQtWctF5=w122-h92-k-no"
        },
        {
            "position": 18,
            "title": "Der Dutchman",
            "place_id": "ChIJi3_txfcQN4gRMxOF78kmaM0",
            "data_id": "0x883710f7c5ed7f8b:0xcd6826c9ef851333",
            "data_cid": "14801122824101892915",
            "reviews_link": "https://serpapi.com/search.json?data_id=0x883710f7c5ed7f8b%3A0xcd6826c9ef851333&engine=google_maps_reviews&hl=en",
            "photos_link": "https://serpapi.com/search.json?data_id=0x883710f7c5ed7f8b%3A0xcd6826c9ef851333&engine=google_maps_photos&hl=en",
            "gps_coordinates": {
                "latitude": 40.541784899999996,
                "longitude": -81.72201609999999
            },
            "place_id_search": "https://serpapi.com/search.json?data=%214m5%213m4%211s0x883710f7c5ed7f8b%3A0xcd6826c9ef851333%218m2%213d40.541784899999996%214d-81.72201609999999&engine=google_maps&google_domain=google.com&hl=en&start=180&type=place",
            "rating": 4.6,
            "reviews": 5907,
            "price": "$$",
            "type": "Family restaurant",
            "address": "4967 Walnut St, Walnut Creek, OH 44687",
            "open_state": "Open \u22c5 Closes 8PM",
            "hours": "Open \u22c5 Closes 8PM",
            "operating_hours": {
                "saturday": "7AM\u20138PM",
                "sunday": "Closed",
                "monday": "Closed",
                "tuesday": "7AM\u20137PM",
                "wednesday": "7AM\u20137PM",
                "thursday": "7AM\u20137PM",
                "friday": "7AM\u20138PM"
            },
            "phone": "(330) 893-2981",
            "website": "http://www.dhgroup.com/",
            "description": "Amish home cooking with pastoral views. Casual, homey spot offering Amish-style fare, pastoral views & rocking chairs on the front porch.",
            "service_options": {
                "dine_in": true,
                "curbside_pickup": true,
                "delivery": false
            },
            "thumbnail": "https://lh5.googleusercontent.com/p/AF1QipNLYfXzrN-y1nNVXlO0ePR1wvebQSIECpcBc3EX=w163-h92-k-no"
        },
        {
            "position": 19,
            "title": "Biltmore Estate Dining Room",
            "place_id": "ChIJs183vc_yWYgRyFe1uws_0x4",
            "data_id": "0x8859f2cfbd375fb3:0x1ed33f0bbbb557c8",
            "data_cid": "2221188360850200520",
            "reviews_link": "https://serpapi.com/search.json?data_id=0x8859f2cfbd375fb3%3A0x1ed33f0bbbb557c8&engine=google_maps_reviews&hl=en",
            "photos_link": "https://serpapi.com/search.json?data_id=0x8859f2cfbd375fb3%3A0x1ed33f0bbbb557c8&engine=google_maps_photos&hl=en",
            "gps_coordinates": {
                "latitude": 35.5577866,
                "longitude": -82.5805968
            },
            "place_id_search": "https://serpapi.com/search.json?data=%214m5%213m4%211s0x8859f2cfbd375fb3%3A0x1ed33f0bbbb557c8%218m2%213d35.5577866%214d-82.5805968&engine=google_maps&google_domain=google.com&hl=en&start=180&type=place",
            "rating": 4.6,
            "reviews": 205,
            "type": "Fine dining restaurant",
            "address": "1 Antler Hill Rd, Asheville, NC 28803",
            "open_state": "Open \u22c5 Closes 12AM",
            "hours": "Open \u22c5 Closes 12AM",
            "operating_hours": {
                "saturday": "11:30AM\u201312AM",
                "sunday": "11:30AM\u201312AM",
                "monday": "11:30AM\u201312AM",
                "tuesday": "11:30AM\u201312AM",
                "wednesday": "11:30AM\u201312AM",
                "thursday": "11:30AM\u201312AM",
                "friday": "11:30AM\u201312AM"
            },
            "phone": "(828) 225-1699",
            "website": "http://www.biltmore.com/visit/dining/dining-room.asp",
            "description": "Formal hotel choice for American cuisine. Genteel dining room at the Biltmore House featuring seasonal American fare, wine & mountain views.",
            "service_options": {
                "dine_in": true,
                "takeout": true,
                "delivery": false
            },
            "thumbnail": "https://lh5.googleusercontent.com/p/AF1QipOzoQOBwYG8ZFGHDnVd8NSg9vq1XPxZH_zxSe-T=w80-h142-k-no"
        },
        {
            "position": 20,
            "title": "Brennan's",
            "place_id": "ChIJjbdq3A2mIIYRCrLg6e3eRy8",
            "data_id": "0x8620a60ddc6ab78d:0x2f47deede9e0b20a",
            "data_cid": "3406936756541501962",
            "reviews_link": "https://serpapi.com/search.json?data_id=0x8620a60ddc6ab78d%3A0x2f47deede9e0b20a&engine=google_maps_reviews&hl=en",
            "photos_link": "https://serpapi.com/search.json?data_id=0x8620a60ddc6ab78d%3A0x2f47deede9e0b20a&engine=google_maps_photos&hl=en",
            "gps_coordinates": {
                "latitude": 29.9561453,
                "longitude": -90.06664599999999
            },
            "place_id_search": "https://serpapi.com/search.json?data=%214m5%213m4%211s0x8620a60ddc6ab78d%3A0x2f47deede9e0b20a%218m2%213d29.9561453%214d-90.06664599999999&engine=google_maps&google_domain=google.com&hl=en&start=180&type=place",
            "rating": 4.6,
            "reviews": 3733,
            "price": "$$$",
            "type": "Restaurant",
            "address": "417 Royal St, New Orleans, LA 70130",
            "open_state": "Closed \u22c5 Opens 6PM",
            "hours": "Closed \u22c5 Opens 6PM",
            "operating_hours": {
                "saturday": "9AM\u20132PM",
                "sunday": "9AM\u20132PM",
                "monday": "9AM\u20132PM",
                "tuesday": "Closed",
                "wednesday": "Closed",
                "thursday": "9AM\u20132PM",
                "friday": "9AM\u20132PM"
            },
            "phone": "(504) 525-9711",
            "website": "https://www.brennansneworleans.com/",
            "description": "Traditional spot for upscale Creole fare. Fine-dining landmark famed for Creole cuisine, posh breakfasts and bananas Foster for dessert.",
            "service_options": {
                "dine_in": true,
                "curbside_pickup": true,
                "delivery": false
            },
            "editorial_reviews": {
                "summary": "The 100 Best USA Brunch Restaurants in 2019",
                "link": "https://www.fsdbco.com/the-100-best-usa-brunch-restaurants-in-2019/",
                "thumbnail": "//www.google.com/s2/favicons?domain=www.fsdbco.com&sz=16"
            },
            "thumbnail": "https://lh5.googleusercontent.com/p/AF1QipMdr_fzvYSXkzPxmx9Vt4NnxNWz2e3Z9RClzvDJ=w138-h92-k-no"
        }
    ],
    "serpapi_pagination": {
        "next": "https://serpapi.com/search.json?engine=google_maps&google_domain=google.com&hl=en&ll=%4043.074761%2C-89.3837613%2C15.1z&q=restaurants&start=200&type=search",
        "current": "https://serpapi.com/search.json?engine=google_maps&google_domain=google.com&hl=en&ll=%4043.074761%2C-89.3837613%2C15.1z&q=restaurants&start=180&type=search",
        "previous": "https://serpapi.com/search.json?engine=google_maps&google_domain=google.com&hl=en&ll=%4043.074761%2C-89.3837613%2C15.1z&q=restaurants&start=160&type=search"
    }
}