{
    "search_metadata": {
        "id": "63710e34d04d6d4fb3161245",
        "status": "Success",
        "json_endpoint": "https://serpapi.com/searches/62829c4705c39f45/63710e34d04d6d4fb3161245.json",
        "created_at": "2022-11-13 15:33:08 UTC",
        "processed_at": "2022-11-13 15:33:08 UTC",
        "google_maps_photos_url": "https://www.google.com/maps/preview/photo?hl=en&pb=!1e2!3m3!1s0x8085807d3f01a483:0xa8e386b194f11d36!9e0!11s!5m58!2m2!1i203!2i100!3m2!2i20!5b1!7m50!1m3!1e1!2b0!3e3!1m3!1e2!2b1!3e2!1m3!1e2!2b0!3e3!1m3!1e3!2b0!3e3!1m3!1e8!2b0!3e3!1m3!1e3!2b1!3e2!1m3!1e10!2b0!3e3!1m3!1e10!2b1!3e2!1m3!1e9!2b1!3e2!1m3!1e10!2b0!3e3!1m3!1e10!2b1!3e2!1m3!1e10!2b0!3e4!2b1!4b1!9b0!6m3!1s!2z!7e81!16m4!1m1!1BCgIYIA!2b1!4e1",
        "raw_html_file": "https://serpapi.com/searches/62829c4705c39f45/63710e34d04d6d4fb3161245.html",
        "prettify_html_file": "https://serpapi.com/searches/62829c4705c39f45/63710e34d04d6d4fb3161245.prettify",
        "total_time_taken": 0.23
    },
    "search_parameters": {
        "engine": "google_maps_photos",
        "data_id": "0x8085807d3f01a483:0xa8e386b194f11d36",
        "hl": "en",
        "category_id": "CgIYIA"
    },
    "categories": [
        {
            "title": "All",
            "id": "CgIgAQ"
        },
        {
            "title": "Latest",
            "id": "CgIgARICGAI"
        },
        {
            "title": "Menu",
            "id": "CgIYIQ"
        },
        {
            "title": "Food & drink",
            "id": "CgIYIA"
        },
        {
            "title": "Vibe",
            "id": "CgIYIg"
        },
        {
            "title": "Sea bass",
            "id": "Cg4qCi9tLzA0aGRsemswCw"
        },
        {
            "title": "Couscous",
            "id": "CgwqCC9tLzAxejZzMAs"
        },
        {
            "title": "Edamame",
            "id": "Cg4qCi9tLzAyd3Y2YjgwCw"
        },
        {
            "title": "Oyster",
            "id": "CgwqCC9tLzBfY3A1MAs"
        },
        {
            "title": "Mackerel",
            "id": "CgwqCC9tLzBjcXE1MAs"
        },
        {
            "title": "Cannoli",
            "id": "CgwqCC9tLzBiMWxrMAs"
        },
        {
            "title": "Steak tartare",
            "id": "Cg0qCS9tLzAzZjVfdzAL"
        },
        {
            "title": "Street View & 360\u00b0",
            "id": "CgIgARICCAI"
        },
        {
            "title": "Videos",
            "id": "CgIgARICCAQ"
        }
    ],
    "photos": [
        {
            "thumbnail": "https://lh5.googleusercontent.com/p/AF1QipOGHYSz-YFAKwb28jo1Dg_F7d-EwaE4lMr5-R74=w203-h152-k-no",
            "image": "https://lh5.googleusercontent.com/p/AF1QipOGHYSz-YFAKwb28jo1Dg_F7d-EwaE4lMr5-R74=w4032-h3024-k-no"
        },
        {
            "thumbnail": "https://lh5.googleusercontent.com/p/AF1QipOwZ5__VUFLg89a6diddw_kDSNaK3uVDCEGGTvr=w203-h135-k-no",
            "image": "https://lh5.googleusercontent.com/p/AF1QipOwZ5__VUFLg89a6diddw_kDSNaK3uVDCEGGTvr=w8368-h5584-k-no"
        },
        {
            "thumbnail": "https://lh5.googleusercontent.com/p/AF1QipPUfUaKaIixf3FL1d_PMOoAWmcVOOHeQ7cCQEmg=w203-h253-k-no",
            "image": "https://lh5.googleusercontent.com/p/AF1QipPUfUaKaIixf3FL1d_PMOoAWmcVOOHeQ7cCQEmg=w1440-h1800-k-no"
        },
        {
            "thumbnail": "https://lh5.googleusercontent.com/p/AF1QipNlWZDRk2Z447MtotSzPYHC74TTJmvr69gbyqb_=w203-h152-k-no",
            "image": "https://lh5.googleusercontent.com/p/AF1QipNlWZDRk2Z447MtotSzPYHC74TTJmvr69gbyqb_=w4032-h3024-k-no"
        },
        {
            "thumbnail": "https://lh5.googleusercontent.com/p/AF1QipOMXMoGcjP3s7mLbXcDzRkfvKuwctUxck8-9QQC=w203-h360-k-no",
            "image": "https://lh5.googleusercontent.com/p/AF1QipOMXMoGcjP3s7mLbXcDzRkfvKuwctUxck8-9QQC=w900-h1600-k-no"
        },
        {
            "thumbnail": "https://lh5.googleusercontent.com/p/AF1QipOBl5iUgRJwq_sYxjckckzGq2D_2jGUinqwnrYN=w203-h152-k-no",
            "image": "https://lh5.googleusercontent.com/p/AF1QipOBl5iUgRJwq_sYxjckckzGq2D_2jGUinqwnrYN=w4032-h3024-k-no"
        },
        {
            "thumbnail": "https://lh5.googleusercontent.com/p/AF1QipOv790Fs0bKxKZx3taHlibMRR3kU_YedfYnp2oO=w203-h417-k-no",
            "image": "https://lh5.googleusercontent.com/p/AF1QipOv790Fs0bKxKZx3taHlibMRR3kU_YedfYnp2oO=w1960-h4032-k-no"
        },
        {
            "thumbnail": "https://lh5.googleusercontent.com/p/AF1QipPlelmT4Lj68Qw3xrTp2mLUmyqJhWjumYF4G2R2=w203-h152-k-no",
            "image": "https://lh5.googleusercontent.com/p/AF1QipPlelmT4Lj68Qw3xrTp2mLUmyqJhWjumYF4G2R2=w1434-h1074-k-no"
        },
        {
            "thumbnail": "https://lh5.googleusercontent.com/p/AF1QipMMYD9iaAVaH9EDOlSeEzulZycm2_77QUmr9Hdk=w203-h114-k-no",
            "image": "https://lh5.googleusercontent.com/p/AF1QipMMYD9iaAVaH9EDOlSeEzulZycm2_77QUmr9Hdk=w4032-h2268-k-no"
        },
        {
            "thumbnail": "https://lh5.googleusercontent.com/p/AF1QipPkhIkGSDizGoFZa4zd2YVO8G7VUN-Pejpel1P5=w203-h114-k-no",
            "image": "https://lh5.googleusercontent.com/p/AF1QipPkhIkGSDizGoFZa4zd2YVO8G7VUN-Pejpel1P5=w4032-h2268-k-no"
        },
        {
            "thumbnail": "https://lh5.googleusercontent.com/p/AF1QipPE8SSLDGpjBHivqbnomry0CqFSSgtfzFvkgjww=w203-h270-k-no",
            "image": "https://lh5.googleusercontent.com/p/AF1QipPE8SSLDGpjBHivqbnomry0CqFSSgtfzFvkgjww=w9000-h12000-k-no"
        },
        {
            "thumbnail": "https://lh5.googleusercontent.com/p/AF1QipPZ8HuZVyx9fH2bOdyN3YHLi6R6bTnprvpDBoy-=w203-h114-k-no",
            "image": "https://lh5.googleusercontent.com/p/AF1QipPZ8HuZVyx9fH2bOdyN3YHLi6R6bTnprvpDBoy-=w4032-h2268-k-no"
        },
        {
            "thumbnail": "https://lh5.googleusercontent.com/p/AF1QipMchhzxclnQsS_wZcGPhJse4X38hQQK2yShH7Df=w203-h152-k-no",
            "image": "https://lh5.googleusercontent.com/p/AF1QipMchhzxclnQsS_wZcGPhJse4X38hQQK2yShH7Df=w4032-h3024-k-no"
        },
        {
            "thumbnail": "https://lh5.googleusercontent.com/p/AF1QipMWHYPUP6DSQvIn34Mk2PHCyci7HquYqTMnGmNi=w203-h152-k-no",
            "image": "https://lh5.googleusercontent.com/p/AF1QipMWHYPUP6DSQvIn34Mk2PHCyci7HquYqTMnGmNi=w4032-h3024-k-no"
        },
        {
            "thumbnail": "https://lh5.googleusercontent.com/p/AF1QipO8zl3c4tBLcxaEABgLdGxg4cxK1susQa610_gd=w203-h152-k-no",
            "image": "https://lh5.googleusercontent.com/p/AF1QipO8zl3c4tBLcxaEABgLdGxg4cxK1susQa610_gd=w4032-h3024-k-no"
        },
        {
            "thumbnail": "https://lh5.googleusercontent.com/p/AF1QipM0yqL1IvEzUv2Iqeour9i0VErKSWPoDPAbC0yB=w203-h152-k-no",
            "image": "https://lh5.googleusercontent.com/p/AF1QipM0yqL1IvEzUv2Iqeour9i0VErKSWPoDPAbC0yB=w4080-h3072-k-no"
        },
        {
            "thumbnail": "https://lh5.googleusercontent.com/p/AF1QipMqd2Rw0w4Sj1Ezs7nQ9zGGguWEWIGuLwVr6DmX=w203-h270-k-no",
            "image": "https://lh5.googleusercontent.com/p/AF1QipMqd2Rw0w4Sj1Ezs7nQ9zGGguWEWIGuLwVr6DmX=w3024-h4032-k-no"
        },
        {
            "thumbnail": "https://lh5.googleusercontent.com/p/AF1QipPNkZobgviOojMlsh92ccLLIplLkCZ-U0shXUnU=w203-h202-k-no",
            "image": "https://lh5.googleusercontent.com/p/AF1QipPNkZobgviOojMlsh92ccLLIplLkCZ-U0shXUnU=w1000-h999-k-no"
        },
        {
            "thumbnail": "https://lh5.googleusercontent.com/p/AF1QipMyev_ydwHcVJ2E5Kn8ZFxcXHevX3UgWnj5wh96=w203-h152-k-no",
            "image": "https://lh5.googleusercontent.com/p/AF1QipMyev_ydwHcVJ2E5Kn8ZFxcXHevX3UgWnj5wh96=w4032-h3024-k-no"
        },
        {
            "thumbnail": "https://lh5.googleusercontent.com/p/AF1QipMDm1hutE5y7i0kBrkvxQh8iwjb_i-DGVHeZOiC=w203-h135-k-no",
            "image": "https://lh5.googleusercontent.com/p/AF1QipMDm1hutE5y7i0kBrkvxQh8iwjb_i-DGVHeZOiC=w2337-h1558-k-no"
        }
    ],
    "serpapi_pagination": {
        "next": "https://serpapi.com/search.json?category_id=CgIYIA&data_id=0x8085807d3f01a483%3A0xa8e386b194f11d36&engine=google_maps_photos&hl=en&next_page_token=EvgDKYQi49-NlUMIDwAAAAEAAAMAAAAIAAAYQAAAAAAAAAAAAAAAAAAAAgAAAAAAAAAAAAIAAAAAAAAAAgAAAAAAAAAAQAAAAAAAAAAAAAAAAAAAAAAAAAIgAAAAAAAAAAAAAAAAgAAABAAAAAAQAAEACBAAAAAAAAAAAAAAAAAAAAAAAAAAQAAAAAAAAAAAAAAAAAAAAAAAAAAQAAAAAAAAAAAAAEAAIAAAAAgAAAAAAAAAADAAAAAAAAAAAAAAAAAAAEAAAAAAAAAAAAAAAAAAAAABAAAAQAAAAAAAAAAEAAAAAAAAAAAACAAAAAAAAAAEAAAAAAAAAAAAAAAAAAAAAAAAAAAAAAAAAAAAAAAAAAAAAAAAAAAAAAAAAAAAAAAAAAAAAACAAAAQAAAAAgAAAAAAAAAAAAgAAAAAAAEAQAAAIAAEAAAAAAAAAAAAAAAAAAAQAAAIAAAAAAAAIAAAAAAAAAAQAAAAAAAAABAAAAAAAAAAAAAAAIAAAAAAAAgAAAAAEAAAAAAAAAAAAAAAAAAAAAAAAAAAAAAAAAAACAAEAEAAAAAACAAAQAAAAAAAEAAAAAAAAAAIAAAEAAAAAAAAAAAAEAAAAAAAAAAAAAAAAAAAAAAgAAAABAAAAAAAAAAAAAAAAIAAAACAAAAAAQAQAAAAAAAAGBRCVCmEIuPfjZVD6AEAACAAAAADAAAAEAAAAAQAFhARAIAAABgASAAEACAIIJAAACBgAAAGAIBEkRDQQCAIARBQAAgCCEAIQQIARAgQIgAIABwACAAAAA",
        "next_page_token": "EvgDKYQi49-NlUMIDwAAAAEAAAMAAAAIAAAYQAAAAAAAAAAAAAAAAAAAAgAAAAAAAAAAAAIAAAAAAAAAAgAAAAAAAAAAQAAAAAAAAAAAAAAAAAAAAAAAAAIgAAAAAAAAAAAAAAAAgAAABAAAAAAQAAEACBAAAAAAAAAAAAAAAAAAAAAAAAAAQAAAAAAAAAAAAAAAAAAAAAAAAAAQAAAAAAAAAAAAAEAAIAAAAAgAAAAAAAAAADAAAAAAAAAAAAAAAAAAAEAAAAAAAAAAAAAAAAAAAAABAAAAQAAAAAAAAAAEAAAAAAAAAAAACAAAAAAAAAAEAAAAAAAAAAAAAAAAAAAAAAAAAAAAAAAAAAAAAAAAAAAAAAAAAAAAAAAAAAAAAAAAAAAAAACAAAAQAAAAAgAAAAAAAAAAAAgAAAAAAAEAQAAAIAAEAAAAAAAAAAAAAAAAAAAQAAAIAAAAAAAAIAAAAAAAAAAQAAAAAAAAABAAAAAAAAAAAAAAAIAAAAAAAAgAAAAAEAAAAAAAAAAAAAAAAAAAAAAAAAAAAAAAAAAACAAEAEAAAAAACAAAQAAAAAAAEAAAAAAAAAAIAAAEAAAAAAAAAAAAEAAAAAAAAAAAAAAAAAAAAAAgAAAABAAAAAAAAAAAAAAAAIAAAACAAAAAAQAQAAAAAAAAGBRCVCmEIuPfjZVD6AEAACAAAAADAAAAEAAAAAQAFhARAIAAABgASAAEACAIIJAAACBgAAAGAIBEkRDQQCAIARBQAAgCCEAIQQIARAgQIgAIABwACAAAAA"
    }
}